[{"childs":[{"name":"path","closed":true,"segments":[{"point":[1.6,27]},{"point":[1.6,3]},{"point":[30.400000000000002,3]},{"point":[30.400000000000002,27]}]},{"name":"path","closed":true,"segments":[{"point":[1.6,5.4],"handleOut":[1.6,4.07]},{"point":[4,3],"handleIn":[2.67,3]},{"point":[28,3],"handleOut":[29.33,3]},{"point":[30.4,5.4],"handleIn":[30.4,4.07]},{"point":[30.4,7.8]},{"point":[1.6,7.8]}]},{"name":"path","closed":true,"segments":[{"point":[1.6,5.4],"handleOut":[1.6,4.07]},{"point":[4,3],"handleIn":[2.67,3]},{"point":[28,3],"handleOut":[29.33,3]},{"point":[30.4,5.4],"handleIn":[30.4,4.07]},{"point":[30.4,7.8]},{"point":[1.6,7.8]}]},{"name":"path","closed":true,"segments":[{"point":[1.6,7.8]},{"point":[30.4,7.8]},{"point":[30.4,22.2]},{"point":[1.6,22.2]}]},{"name":"path","closed":true,"segments":[{"point":[1.6,7.8]},{"point":[30.4,7.8]},{"point":[30.4,22.2]},{"point":[1.6,22.2]}]},{"name":"path","closed":true,"fill":"#c0c0c0","segments":[{"point":[1.6,22.2]},{"point":[30.4,22.2]},{"point":[30.4,24.6],"handleOut":[30.4,25.93]},{"point":[28,27],"handleIn":[29.33,27]},{"point":[4,27],"handleOut":[2.67,27]},{"point":[1.6,24.6],"handleIn":[1.6,25.93]}]},{"name":"path","closed":true,"segments":[{"point":[1.6,22.2]},{"point":[30.4,22.2]},{"point":[30.4,24.6],"handleOut":[30.4,25.93]},{"point":[28,27],"handleIn":[29.33,27]},{"point":[4,27],"handleOut":[2.67,27]},{"point":[1.6,24.6],"handleIn":[1.6,25.93]}]}]},{"childs":[{"name":"path","closed":true,"segments":[{"point":[1.6,27]},{"point":[1.6,3]},{"point":[30.400000000000002,3]},{"point":[30.400000000000002,27]}]},{"name":"path","closed":true,"segments":[{"point":[1.6,5.4],"handleOut":[1.6,4.07]},{"point":[4,3],"handleIn":[2.67,3]},{"point":[28,3],"handleOut":[29.33,3]},{"point":[30.4,5.4],"handleIn":[30.4,4.07]},{"point":[30.4,7.8]},{"point":[1.6,7.8]}]},{"name":"path","closed":true,"segments":[{"point":[1.6,5.4],"handleOut":[1.6,4.07]},{"point":[4,3],"handleIn":[2.67,3]},{"point":[28,3],"handleOut":[29.33,3]},{"point":[30.4,5.4],"handleIn":[30.4,4.07]},{"point":[30.4,7.8]},{"point":[1.6,7.8]}]},{"name":"path","closed":true,"segments":[{"point":[1.6,7.8]},{"point":[30.4,7.8]},{"point":[30.4,22.2]},{"point":[1.6,22.2]}]},{"name":"path","closed":true,"segments":[{"point":[1.6,7.8]},{"point":[30.4,7.8]},{"point":[30.4,22.2]},{"point":[1.6,22.2]}]},{"name":"path","closed":false,"segments":[{"point":[15.26,21.62],"handleOut":[14.76,21.22]},{"point":[14.93,19.91],"handleIn":[14.61,20.48],"handleOut":[15.25,19.33]},{"point":[16.52,19.33],"handleIn":[15.92,19.08],"handleOut":[17.11,19.57]},{"point":[17.29,20.89],"handleIn":[17.44,20.24],"handleOut":[17.13,21.53]},{"point":[15.9,21.89],"handleIn":[16.54,21.96]}]},{"name":"path","closed":false,"segments":[{"point":[15.26,20.96]},{"point":[15.26,21.62]},{"point":[14.56,21.42]}]},{"name":"path","closed":true,"fill":"#c0c0c0","segments":[{"point":[1.6,22.2]},{"point":[30.4,22.2]},{"point":[30.4,24.6],"handleOut":[30.4,25.93]},{"point":[28,27],"handleIn":[29.33,27]},{"point":[4,27],"handleOut":[2.67,27]},{"point":[1.6,24.6],"handleIn":[1.6,25.93]}]},{"name":"path","closed":true,"segments":[{"point":[1.6,22.2]},{"point":[30.4,22.2]},{"point":[30.4,24.6],"handleOut":[30.4,25.93]},{"point":[28,27],"handleIn":[29.33,27]},{"point":[4,27],"handleOut":[2.67,27]},{"point":[1.6,24.6],"handleIn":[1.6,25.93]}]}]},{"childs":[{"name":"path","closed":true,"segments":[{"point":[1.6,27]},{"point":[1.6,3]},{"point":[30.400000000000002,3]},{"point":[30.400000000000002,27]}]},{"name":"path","closed":true,"segments":[{"point":[1.6,5.4],"handleOut":[1.6,4.07]},{"point":[4,3],"handleIn":[2.67,3]},{"point":[28,3],"handleOut":[29.33,3]},{"point":[30.4,5.4],"handleIn":[30.4,4.07]},{"point":[30.4,7.8]},{"point":[1.6,7.8]}]},{"name":"path","closed":true,"segments":[{"point":[1.6,5.4],"handleOut":[1.6,4.07]},{"point":[4,3],"handleIn":[2.67,3]},{"point":[28,3],"handleOut":[29.33,3]},{"point":[30.4,5.4],"handleIn":[30.4,4.07]},{"point":[30.4,7.8]},{"point":[1.6,7.8]}]},{"name":"path","closed":true,"segments":[{"point":[1.6,7.8]},{"point":[30.4,7.8]},{"point":[30.4,22.2]},{"point":[1.6,22.2]}]},{"name":"path","closed":true,"segments":[{"point":[1.6,7.8]},{"point":[30.4,7.8]},{"point":[30.4,22.2]},{"point":[1.6,22.2]}]},{"name":"path","closed":false,"segments":[{"point":[14.56,19.66]},{"point":[17.44,19.66]}]},{"name":"path","closed":false,"segments":[{"point":[14.56,20.52]},{"point":[17.44,20.52]}]},{"name":"path","closed":false,"segments":[{"point":[14.56,21.38]},{"point":[17.44,21.38]}]},{"name":"path","closed":true,"fill":"#c0c0c0","segments":[{"point":[1.6,22.2]},{"point":[30.4,22.2]},{"point":[30.4,24.6],"handleOut":[30.4,25.93]},{"point":[28,27],"handleIn":[29.33,27]},{"point":[4,27],"handleOut":[2.67,27]},{"point":[1.6,24.6],"handleIn":[1.6,25.93]}]},{"name":"path","closed":true,"segments":[{"point":[1.6,22.2]},{"point":[30.4,22.2]},{"point":[30.4,24.6],"handleOut":[30.4,25.93]},{"point":[28,27],"handleIn":[29.33,27]},{"point":[4,27],"handleOut":[2.67,27]},{"point":[1.6,24.6],"handleIn":[1.6,25.93]}]}]},{"childs":[{"name":"path","closed":true,"segments":[{"point":[1.6,27]},{"point":[1.6,3]},{"point":[30.400000000000002,3]},{"point":[30.400000000000002,27]}]},{"name":"path","closed":true,"segments":[{"point":[1.6,5.4],"handleOut":[1.6,4.07]},{"point":[4,3],"handleIn":[2.67,3]},{"point":[28,3],"handleOut":[29.33,3]},{"point":[30.4,5.4],"handleIn":[30.4,4.07]},{"point":[30.4,7.8]},{"point":[1.6,7.8]}]},{"name":"path","closed":true,"segments":[{"point":[1.6,5.4],"handleOut":[1.6,4.07]},{"point":[4,3],"handleIn":[2.67,3]},{"point":[28,3],"handleOut":[29.33,3]},{"point":[30.4,5.4],"handleIn":[30.4,4.07]},{"point":[30.4,7.8]},{"point":[1.6,7.8]}]},{"name":"path","closed":true,"segments":[{"point":[1.6,7.8]},{"point":[30.4,7.8]},{"point":[30.4,22.2]},{"point":[1.6,22.2]}]},{"name":"path","closed":true,"segments":[{"point":[1.6,7.8]},{"point":[30.4,7.8]},{"point":[30.4,22.2]},{"point":[1.6,22.2]}]},{"name":"path","closed":false,"segments":[{"point":[15.14,19.08]},{"point":[15.14,21.96]}]},{"name":"path","closed":false,"segments":[{"point":[16,19.08]},{"point":[16,21.96]}]},{"name":"path","closed":false,"segments":[{"point":[16.86,19.08]},{"point":[16.86,21.96]}]},{"name":"path","closed":true,"fill":"#c0c0c0","segments":[{"point":[1.6,22.2]},{"point":[30.4,22.2]},{"point":[30.4,24.6],"handleOut":[30.4,25.93]},{"point":[28,27],"handleIn":[29.33,27]},{"point":[4,27],"handleOut":[2.67,27]},{"point":[1.6,24.6],"handleIn":[1.6,25.93]}]},{"name":"path","closed":true,"segments":[{"point":[1.6,22.2]},{"point":[30.4,22.2]},{"point":[30.4,24.6],"handleOut":[30.4,25.93]},{"point":[28,27],"handleIn":[29.33,27]},{"point":[4,27],"handleOut":[2.67,27]},{"point":[1.6,24.6],"handleIn":[1.6,25.93]}]}]},{"childs":[{"name":"path","closed":true,"segments":[{"point":[1.6,27]},{"point":[1.6,3]},{"point":[30.400000000000002,3]},{"point":[30.400000000000002,27]}]},{"name":"path","closed":true,"segments":[{"point":[1.6,5.4],"handleOut":[1.6,4.07]},{"point":[4,3],"handleIn":[2.67,3]},{"point":[28,3],"handleOut":[29.33,3]},{"point":[30.4,5.4],"handleIn":[30.4,4.07]},{"point":[30.4,7.8]},{"point":[1.6,7.8]}]},{"name":"path","closed":true,"segments":[{"point":[1.6,5.4],"handleOut":[1.6,4.07]},{"point":[4,3],"handleIn":[2.67,3]},{"point":[28,3],"handleOut":[29.33,3]},{"point":[30.4,5.4],"handleIn":[30.4,4.07]},{"point":[30.4,7.8]},{"point":[1.6,7.8]}]},{"name":"path","closed":true,"segments":[{"point":[1.6,7.8]},{"point":[30.4,7.8]},{"point":[30.4,22.2]},{"point":[1.6,22.2]}]},{"name":"path","closed":true,"segments":[{"point":[1.6,7.8]},{"point":[30.4,7.8]},{"point":[30.4,22.2]},{"point":[1.6,22.2]}]},{"name":"path","closed":true,"segments":[{"point":[14.32,22.2]},{"point":[14.32,18.84]},{"point":[17.68,18.84]},{"point":[17.68,22.2]}]},{"name":"path","closed":false,"segments":[{"point":[15.28,20.52]},{"point":[16.72,20.52]}]},{"name":"path","closed":false,"segments":[{"point":[16,19.8]},{"point":[16,21.24]}]},{"name":"path","closed":true,"fill":"#c0c0c0","segments":[{"point":[1.6,22.2]},{"point":[30.4,22.2]},{"point":[30.4,24.6],"handleOut":[30.4,25.93]},{"point":[28,27],"handleIn":[29.33,27]},{"point":[4,27],"handleOut":[2.67,27]},{"point":[1.6,24.6],"handleIn":[1.6,25.93]}]},{"name":"path","closed":true,"segments":[{"point":[1.6,22.2]},{"point":[30.4,22.2]},{"point":[30.4,24.6],"handleOut":[30.4,25.93]},{"point":[28,27],"handleIn":[29.33,27]},{"point":[4,27],"handleOut":[2.67,27]},{"point":[1.6,24.6],"handleIn":[1.6,25.93]}]}]},{"childs":[{"name":"path","closed":true,"segments":[{"point":[1.6,27]},{"point":[1.6,3]},{"point":[30.400000000000002,3]},{"point":[30.400000000000002,27]}]},{"name":"path","closed":true,"segments":[{"point":[1.6,5.4],"handleOut":[1.6,4.07]},{"point":[4,3],"handleIn":[2.67,3]},{"point":[28,3],"handleOut":[29.33,3]},{"point":[30.4,5.4],"handleIn":[30.4,4.07]},{"point":[30.4,7.8]},{"point":[1.6,7.8]}]},{"name":"path","closed":true,"segments":[{"point":[1.6,5.4],"handleOut":[1.6,4.07]},{"point":[4,3],"handleIn":[2.67,3]},{"point":[28,3],"handleOut":[29.33,3]},{"point":[30.4,5.4],"handleIn":[30.4,4.07]},{"point":[30.4,7.8]},{"point":[1.6,7.8]}]},{"name":"path","closed":true,"segments":[{"point":[1.6,7.8]},{"point":[30.4,7.8]},{"point":[30.4,22.2]},{"point":[1.6,22.2]}]},{"name":"path","closed":true,"segments":[{"point":[1.6,7.8]},{"point":[30.4,7.8]},{"point":[30.4,22.2]},{"point":[1.6,22.2]}]},{"name":"path","closed":false,"segments":[{"point":[13.58,21.62],"handleOut":[13.08,21.22]},{"point":[13.25,19.91],"handleIn":[12.93,20.48],"handleOut":[13.57,19.33]},{"point":[14.84,19.33],"handleIn":[14.24,19.08],"handleOut":[15.43,19.57]},{"point":[15.61,20.89],"handleIn":[15.76,20.24],"handleOut":[15.45,21.53]},{"point":[14.22,21.89],"handleIn":[14.86,21.96]}]},{"name":"path","closed":false,"segments":[{"point":[13.58,20.96]},{"point":[13.58,21.62]},{"point":[12.88,21.42]}]},{"name":"path","closed":true,"segments":[{"point":[16,22.2]},{"point":[16,18.84]},{"point":[19.36,18.84]},{"point":[19.36,22.2]}]},{"name":"path","closed":false,"segments":[{"point":[16.96,20.52]},{"point":[18.4,20.52]}]},{"name":"path","closed":false,"segments":[{"point":[17.68,19.8]},{"point":[17.68,21.24]}]},{"name":"path","closed":true,"fill":"#c0c0c0","segments":[{"point":[1.6,22.2]},{"point":[30.4,22.2]},{"point":[30.4,24.6],"handleOut":[30.4,25.93]},{"point":[28,27],"handleIn":[29.33,27]},{"point":[4,27],"handleOut":[2.67,27]},{"point":[1.6,24.6],"handleIn":[1.6,25.93]}]},{"name":"path","closed":true,"segments":[{"point":[1.6,22.2]},{"point":[30.4,22.2]},{"point":[30.4,24.6],"handleOut":[30.4,25.93]},{"point":[28,27],"handleIn":[29.33,27]},{"point":[4,27],"handleOut":[2.67,27]},{"point":[1.6,24.6],"handleIn":[1.6,25.93]}]}]},{"childs":[{"name":"path","closed":true,"segments":[{"point":[1.6,27]},{"point":[1.6,3]},{"point":[30.400000000000002,3]},{"point":[30.400000000000002,27]}]},{"name":"path","closed":true,"segments":[{"point":[1.6,5.4],"handleOut":[1.6,4.07]},{"point":[4,3],"handleIn":[2.67,3]},{"point":[28,3],"handleOut":[29.33,3]},{"point":[30.4,5.4],"handleIn":[30.4,4.07]},{"point":[30.4,7.8]},{"point":[1.6,7.8]}]},{"name":"path","closed":true,"segments":[{"point":[1.6,5.4],"handleOut":[1.6,4.07]},{"point":[4,3],"handleIn":[2.67,3]},{"point":[28,3],"handleOut":[29.33,3]},{"point":[30.4,5.4],"handleIn":[30.4,4.07]},{"point":[30.4,7.8]},{"point":[1.6,7.8]}]},{"name":"path","closed":true,"segments":[{"point":[1.6,7.8]},{"point":[30.4,7.8]},{"point":[30.4,22.2]},{"point":[1.6,22.2]}]},{"name":"path","closed":true,"segments":[{"point":[1.6,7.8]},{"point":[30.4,7.8]},{"point":[30.4,22.2]},{"point":[1.6,22.2]}]},{"name":"path","closed":false,"segments":[{"point":[12.88,19.66]},{"point":[15.76,19.66]}]},{"name":"path","closed":false,"segments":[{"point":[12.88,20.52]},{"point":[15.76,20.52]}]},{"name":"path","closed":false,"segments":[{"point":[12.88,21.38]},{"point":[15.76,21.38]}]},{"name":"path","closed":true,"segments":[{"point":[16,22.2]},{"point":[16,18.84]},{"point":[19.36,18.84]},{"point":[19.36,22.2]}]},{"name":"path","closed":false,"segments":[{"point":[16.96,20.52]},{"point":[18.4,20.52]}]},{"name":"path","closed":false,"segments":[{"point":[17.68,19.8]},{"point":[17.68,21.24]}]},{"name":"path","closed":true,"fill":"#c0c0c0","segments":[{"point":[1.6,22.2]},{"point":[30.4,22.2]},{"point":[30.4,24.6],"handleOut":[30.4,25.93]},{"point":[28,27],"handleIn":[29.33,27]},{"point":[4,27],"handleOut":[2.67,27]},{"point":[1.6,24.6],"handleIn":[1.6,25.93]}]},{"name":"path","closed":true,"segments":[{"point":[1.6,22.2]},{"point":[30.4,22.2]},{"point":[30.4,24.6],"handleOut":[30.4,25.93]},{"point":[28,27],"handleIn":[29.33,27]},{"point":[4,27],"handleOut":[2.67,27]},{"point":[1.6,24.6],"handleIn":[1.6,25.93]}]}]},{"childs":[{"name":"path","closed":true,"segments":[{"point":[1.6,27]},{"point":[1.6,3]},{"point":[30.400000000000002,3]},{"point":[30.400000000000002,27]}]},{"name":"path","closed":true,"segments":[{"point":[1.6,5.4],"handleOut":[1.6,4.07]},{"point":[4,3],"handleIn":[2.67,3]},{"point":[28,3],"handleOut":[29.33,3]},{"point":[30.4,5.4],"handleIn":[30.4,4.07]},{"point":[30.4,7.8]},{"point":[1.6,7.8]}]},{"name":"path","closed":true,"segments":[{"point":[1.6,5.4],"handleOut":[1.6,4.07]},{"point":[4,3],"handleIn":[2.67,3]},{"point":[28,3],"handleOut":[29.33,3]},{"point":[30.4,5.4],"handleIn":[30.4,4.07]},{"point":[30.4,7.8]},{"point":[1.6,7.8]}]},{"name":"path","closed":true,"segments":[{"point":[1.6,7.8]},{"point":[30.4,7.8]},{"point":[30.4,22.2]},{"point":[1.6,22.2]}]},{"name":"path","closed":true,"segments":[{"point":[1.6,7.8]},{"point":[30.4,7.8]},{"point":[30.4,22.2]},{"point":[1.6,22.2]}]},{"name":"path","closed":false,"segments":[{"point":[13.46,19.08]},{"point":[13.46,21.96]}]},{"name":"path","closed":false,"segments":[{"point":[14.32,19.08]},{"point":[14.32,21.96]}]},{"name":"path","closed":false,"segments":[{"point":[15.18,19.08]},{"point":[15.18,21.96]}]},{"name":"path","closed":true,"segments":[{"point":[16,22.2]},{"point":[16,18.84]},{"point":[19.36,18.84]},{"point":[19.36,22.2]}]},{"name":"path","closed":false,"segments":[{"point":[16.96,20.52]},{"point":[18.4,20.52]}]},{"name":"path","closed":false,"segments":[{"point":[17.68,19.8]},{"point":[17.68,21.24]}]},{"name":"path","closed":true,"fill":"#c0c0c0","segments":[{"point":[1.6,22.2]},{"point":[30.4,22.2]},{"point":[30.4,24.6],"handleOut":[30.4,25.93]},{"point":[28,27],"handleIn":[29.33,27]},{"point":[4,27],"handleOut":[2.67,27]},{"point":[1.6,24.6],"handleIn":[1.6,25.93]}]},{"name":"path","closed":true,"segments":[{"point":[1.6,22.2]},{"point":[30.4,22.2]},{"point":[30.4,24.6],"handleOut":[30.4,25.93]},{"point":[28,27],"handleIn":[29.33,27]},{"point":[4,27],"handleOut":[2.67,27]},{"point":[1.6,24.6],"handleIn":[1.6,25.93]}]}]},{"childs":[{"name":"path","closed":true,"segments":[{"point":[2,22]},{"point":[2,8]},{"point":[30,8]},{"point":[30,22]}]},{"name":"path","closed":true,"segments":[{"point":[2,8.7],"handleOut":[2,8.31]},{"point":[2.7,8],"handleIn":[2.31,8]},{"point":[29.3,8],"handleOut":[29.69,8]},{"point":[30,8.7],"handleIn":[30,8.31]},{"point":[30,9.4]},{"point":[2,9.4]}]},{"name":"path","closed":true,"segments":[{"point":[2,8.7],"handleOut":[2,8.31]},{"point":[2.7,8],"handleIn":[2.31,8]},{"point":[29.3,8],"handleOut":[29.69,8]},{"point":[30,8.7],"handleIn":[30,8.31]},{"point":[30,9.4]},{"point":[2,9.4]}]},{"name":"path","closed":true,"segments":[{"point":[2,9.4]},{"point":[30,9.4]},{"point":[30,20.6]},{"point":[2,20.6]}]},{"name":"path","closed":true,"segments":[{"point":[2,9.4]},{"point":[30,9.4]},{"point":[30,20.6]},{"point":[2,20.6]}]},{"name":"path","closed":true,"fill":"#c0c0c0","segments":[{"point":[2,20.6]},{"point":[30,20.6]},{"point":[30,21.3],"handleOut":[30,21.69]},{"point":[29.3,22],"handleIn":[29.69,22]},{"point":[2.7,22],"handleOut":[2.31,22]},{"point":[2,21.3],"handleIn":[2,21.69]}]},{"name":"path","closed":true,"segments":[{"point":[2,20.6]},{"point":[30,20.6]},{"point":[30,21.3],"handleOut":[30,21.69]},{"point":[29.3,22],"handleIn":[29.69,22]},{"point":[2.7,22],"handleOut":[2.31,22]},{"point":[2,21.3],"handleIn":[2,21.69]}]}]},{"childs":[{"name":"path","closed":true,"segments":[{"point":[1.6,27]},{"point":[1.6,3]},{"point":[30.400000000000002,3]},{"point":[30.400000000000002,27]}]}]},{"childs":[{"name":"path","closed":true,"segments":[{"point":[2.2,26.5]},{"point":[2.2,3.5]},{"point":[29.8,3.5]},{"point":[29.8,26.5]}]},{"name":"path","closed":true,"segments":[{"point":[2.2,5.8],"handleOut":[2.2,4.53]},{"point":[4.5,3.5],"handleIn":[3.23,3.5]},{"point":[27.5,3.5],"handleOut":[28.77,3.5]},{"point":[29.8,5.8],"handleIn":[29.8,4.53]},{"point":[29.8,8.1]},{"point":[2.2,8.1]}]},{"name":"path","closed":true,"segments":[{"point":[2.2,5.8],"handleOut":[2.2,4.53]},{"point":[4.5,3.5],"handleIn":[3.23,3.5]},{"point":[27.5,3.5],"handleOut":[28.77,3.5]},{"point":[29.8,5.8],"handleIn":[29.8,4.53]},{"point":[29.8,8.1]},{"point":[2.2,8.1]}]},{"name":"path","closed":true,"segments":[{"point":[2.2,8.1]},{"point":[29.8,8.1]},{"point":[29.8,21.9]},{"point":[2.2,21.9]}]},{"name":"path","closed":true,"segments":[{"point":[2.2,8.1]},{"point":[29.8,8.1]},{"point":[29.8,21.9]},{"point":[2.2,21.9]}]},{"name":"path","closed":true,"fill":"#c0c0c0","segments":[{"point":[2.2,21.9]},{"point":[29.8,21.9]},{"point":[29.8,24.2],"handleOut":[29.8,25.47]},{"point":[27.5,26.5],"handleIn":[28.77,26.5]},{"point":[4.5,26.5],"handleOut":[3.23,26.5]},{"point":[2.2,24.2],"handleIn":[2.2,25.47]}]},{"name":"path","closed":true,"segments":[{"point":[2.2,21.9]},{"point":[29.8,21.9]},{"point":[29.8,24.2],"handleOut":[29.8,25.47]},{"point":[27.5,26.5],"handleIn":[28.77,26.5]},{"point":[4.5,26.5],"handleOut":[3.23,26.5]},{"point":[2.2,24.2],"handleIn":[2.2,25.47]}]}]},{"childs":[{"name":"path","closed":true,"segments":[{"point":[2.2,26.5]},{"point":[2.2,3.5]},{"point":[29.8,3.5]},{"point":[29.8,26.5]}]},{"name":"path","closed":true,"segments":[{"point":[2.2,5.8],"handleOut":[2.2,4.53]},{"point":[4.5,3.5],"handleIn":[3.23,3.5]},{"point":[27.5,3.5],"handleOut":[28.77,3.5]},{"point":[29.8,5.8],"handleIn":[29.8,4.53]},{"point":[29.8,8.1]},{"point":[2.2,8.1]}]},{"name":"path","closed":true,"segments":[{"point":[2.2,5.8],"handleOut":[2.2,4.53]},{"point":[4.5,3.5],"handleIn":[3.23,3.5]},{"point":[27.5,3.5],"handleOut":[28.77,3.5]},{"point":[29.8,5.8],"handleIn":[29.8,4.53]},{"point":[29.8,8.1]},{"point":[2.2,8.1]}]},{"name":"path","closed":true,"segments":[{"point":[2.2,8.1]},{"point":[29.8,8.1]},{"point":[29.8,21.9]},{"point":[2.2,21.9]}]},{"name":"path","closed":true,"segments":[{"point":[2.2,8.1]},{"point":[29.8,8.1]},{"point":[29.8,21.9]},{"point":[2.2,21.9]}]},{"name":"path","closed":false,"segments":[{"point":[15.29,21.35],"handleOut":[14.81,20.96]},{"point":[14.97,19.7],"handleIn":[14.67,20.26],"handleOut":[15.28,19.15]},{"point":[16.5,19.15],"handleIn":[15.93,18.91],"handleOut":[17.07,19.38]},{"point":[17.23,20.64],"handleIn":[17.38,20.02],"handleOut":[17.08,21.26]},{"point":[15.91,21.6],"handleIn":[16.52,21.67]}]},{"name":"path","closed":false,"segments":[{"point":[15.29,20.71]},{"point":[15.29,21.35]},{"point":[14.62,21.15]}]},{"name":"path","closed":true,"fill":"#c0c0c0","segments":[{"point":[2.2,21.9]},{"point":[29.8,21.9]},{"point":[29.8,24.2],"handleOut":[29.8,25.47]},{"point":[27.5,26.5],"handleIn":[28.77,26.5]},{"point":[4.5,26.5],"handleOut":[3.23,26.5]},{"point":[2.2,24.2],"handleIn":[2.2,25.47]}]},{"name":"path","closed":true,"segments":[{"point":[2.2,21.9]},{"point":[29.8,21.9]},{"point":[29.8,24.2],"handleOut":[29.8,25.47]},{"point":[27.5,26.5],"handleIn":[28.77,26.5]},{"point":[4.5,26.5],"handleOut":[3.23,26.5]},{"point":[2.2,24.2],"handleIn":[2.2,25.47]}]}]},{"childs":[{"name":"path","closed":true,"segments":[{"point":[2.2,26.5]},{"point":[2.2,3.5]},{"point":[29.8,3.5]},{"point":[29.8,26.5]}]},{"name":"path","closed":true,"segments":[{"point":[2.2,5.8],"handleOut":[2.2,4.53]},{"point":[4.5,3.5],"handleIn":[3.23,3.5]},{"point":[27.5,3.5],"handleOut":[28.77,3.5]},{"point":[29.8,5.8],"handleIn":[29.8,4.53]},{"point":[29.8,8.1]},{"point":[2.2,8.1]}]},{"name":"path","closed":true,"segments":[{"point":[2.2,5.8],"handleOut":[2.2,4.53]},{"point":[4.5,3.5],"handleIn":[3.23,3.5]},{"point":[27.5,3.5],"handleOut":[28.77,3.5]},{"point":[29.8,5.8],"handleIn":[29.8,4.53]},{"point":[29.8,8.1]},{"point":[2.2,8.1]}]},{"name":"path","closed":true,"segments":[{"point":[2.2,8.1]},{"point":[29.8,8.1]},{"point":[29.8,21.9]},{"point":[2.2,21.9]}]},{"name":"path","closed":true,"segments":[{"point":[2.2,8.1]},{"point":[29.8,8.1]},{"point":[29.8,21.9]},{"point":[2.2,21.9]}]},{"name":"path","closed":false,"segments":[{"point":[14.62,19.46]},{"point":[17.38,19.46]}]},{"name":"path","closed":false,"segments":[{"point":[14.62,20.29]},{"point":[17.38,20.29]}]},{"name":"path","closed":false,"segments":[{"point":[14.62,21.12]},{"point":[17.38,21.12]}]},{"name":"path","closed":true,"fill":"#c0c0c0","segments":[{"point":[2.2,21.9]},{"point":[29.8,21.9]},{"point":[29.8,24.2],"handleOut":[29.8,25.47]},{"point":[27.5,26.5],"handleIn":[28.77,26.5]},{"point":[4.5,26.5],"handleOut":[3.23,26.5]},{"point":[2.2,24.2],"handleIn":[2.2,25.47]}]},{"name":"path","closed":true,"segments":[{"point":[2.2,21.9]},{"point":[29.8,21.9]},{"point":[29.8,24.2],"handleOut":[29.8,25.47]},{"point":[27.5,26.5],"handleIn":[28.77,26.5]},{"point":[4.5,26.5],"handleOut":[3.23,26.5]},{"point":[2.2,24.2],"handleIn":[2.2,25.47]}]}]},{"childs":[{"name":"path","closed":true,"segments":[{"point":[2.2,26.5]},{"point":[2.2,3.5]},{"point":[29.8,3.5]},{"point":[29.8,26.5]}]},{"name":"path","closed":true,"segments":[{"point":[2.2,5.8],"handleOut":[2.2,4.53]},{"point":[4.5,3.5],"handleIn":[3.23,3.5]},{"point":[27.5,3.5],"handleOut":[28.77,3.5]},{"point":[29.8,5.8],"handleIn":[29.8,4.53]},{"point":[29.8,8.1]},{"point":[2.2,8.1]}]},{"name":"path","closed":true,"segments":[{"point":[2.2,5.8],"handleOut":[2.2,4.53]},{"point":[4.5,3.5],"handleIn":[3.23,3.5]},{"point":[27.5,3.5],"handleOut":[28.77,3.5]},{"point":[29.8,5.8],"handleIn":[29.8,4.53]},{"point":[29.8,8.1]},{"point":[2.2,8.1]}]},{"name":"path","closed":true,"segments":[{"point":[2.2,8.1]},{"point":[29.8,8.1]},{"point":[29.8,21.9]},{"point":[2.2,21.9]}]},{"name":"path","closed":true,"segments":[{"point":[2.2,8.1]},{"point":[29.8,8.1]},{"point":[29.8,21.9]},{"point":[2.2,21.9]}]},{"name":"path","closed":false,"segments":[{"point":[15.17,18.91]},{"point":[15.17,21.67]}]},{"name":"path","closed":false,"segments":[{"point":[16,18.91]},{"point":[16,21.67]}]},{"name":"path","closed":false,"segments":[{"point":[16.83,18.91]},{"point":[16.83,21.67]}]},{"name":"path","closed":true,"fill":"#c0c0c0","segments":[{"point":[2.2,21.9]},{"point":[29.8,21.9]},{"point":[29.8,24.2],"handleOut":[29.8,25.47]},{"point":[27.5,26.5],"handleIn":[28.77,26.5]},{"point":[4.5,26.5],"handleOut":[3.23,26.5]},{"point":[2.2,24.2],"handleIn":[2.2,25.47]}]},{"name":"path","closed":true,"segments":[{"point":[2.2,21.9]},{"point":[29.8,21.9]},{"point":[29.8,24.2],"handleOut":[29.8,25.47]},{"point":[27.5,26.5],"handleIn":[28.77,26.5]},{"point":[4.5,26.5],"handleOut":[3.23,26.5]},{"point":[2.2,24.2],"handleIn":[2.2,25.47]}]}]},{"childs":[{"name":"path","closed":true,"segments":[{"point":[2.2,26.5]},{"point":[2.2,3.5]},{"point":[29.8,3.5]},{"point":[29.8,26.5]}]},{"name":"path","closed":true,"segments":[{"point":[2.2,5.8],"handleOut":[2.2,4.53]},{"point":[4.5,3.5],"handleIn":[3.23,3.5]},{"point":[27.5,3.5],"handleOut":[28.77,3.5]},{"point":[29.8,5.8],"handleIn":[29.8,4.53]},{"point":[29.8,8.1]},{"point":[2.2,8.1]}]},{"name":"path","closed":true,"segments":[{"point":[2.2,5.8],"handleOut":[2.2,4.53]},{"point":[4.5,3.5],"handleIn":[3.23,3.5]},{"point":[27.5,3.5],"handleOut":[28.77,3.5]},{"point":[29.8,5.8],"handleIn":[29.8,4.53]},{"point":[29.8,8.1]},{"point":[2.2,8.1]}]},{"name":"path","closed":true,"segments":[{"point":[2.2,8.1]},{"point":[29.8,8.1]},{"point":[29.8,21.9]},{"point":[2.2,21.9]}]},{"name":"path","closed":true,"segments":[{"point":[2.2,8.1]},{"point":[29.8,8.1]},{"point":[29.8,21.9]},{"point":[2.2,21.9]}]},{"name":"path","closed":true,"segments":[{"point":[14.39,21.9]},{"point":[14.39,18.68]},{"point":[17.61,18.68]},{"point":[17.61,21.9]}]},{"name":"path","closed":false,"segments":[{"point":[15.31,20.29]},{"point":[16.69,20.29]}]},{"name":"path","closed":false,"segments":[{"point":[16,19.6]},{"point":[16,20.98]}]},{"name":"path","closed":true,"fill":"#c0c0c0","segments":[{"point":[2.2,21.9]},{"point":[29.8,21.9]},{"point":[29.8,24.2],"handleOut":[29.8,25.47]},{"point":[27.5,26.5],"handleIn":[28.77,26.5]},{"point":[4.5,26.5],"handleOut":[3.23,26.5]},{"point":[2.2,24.2],"handleIn":[2.2,25.47]}]},{"name":"path","closed":true,"segments":[{"point":[2.2,21.9]},{"point":[29.8,21.9]},{"point":[29.8,24.2],"handleOut":[29.8,25.47]},{"point":[27.5,26.5],"handleIn":[28.77,26.5]},{"point":[4.5,26.5],"handleOut":[3.23,26.5]},{"point":[2.2,24.2],"handleIn":[2.2,25.47]}]}]},{"childs":[{"name":"path","closed":true,"segments":[{"point":[2.2,26.5]},{"point":[2.2,3.5]},{"point":[29.8,3.5]},{"point":[29.8,26.5]}]},{"name":"path","closed":true,"segments":[{"point":[2.2,5.8],"handleOut":[2.2,4.53]},{"point":[4.5,3.5],"handleIn":[3.23,3.5]},{"point":[27.5,3.5],"handleOut":[28.77,3.5]},{"point":[29.8,5.8],"handleIn":[29.8,4.53]},{"point":[29.8,8.1]},{"point":[2.2,8.1]}]},{"name":"path","closed":true,"segments":[{"point":[2.2,5.8],"handleOut":[2.2,4.53]},{"point":[4.5,3.5],"handleIn":[3.23,3.5]},{"point":[27.5,3.5],"handleOut":[28.77,3.5]},{"point":[29.8,5.8],"handleIn":[29.8,4.53]},{"point":[29.8,8.1]},{"point":[2.2,8.1]}]},{"name":"path","closed":true,"segments":[{"point":[2.2,8.1]},{"point":[29.8,8.1]},{"point":[29.8,21.9]},{"point":[2.2,21.9]}]},{"name":"path","closed":true,"segments":[{"point":[2.2,8.1]},{"point":[29.8,8.1]},{"point":[29.8,21.9]},{"point":[2.2,21.9]}]},{"name":"path","closed":false,"segments":[{"point":[13.68,21.35],"handleOut":[13.2,20.96]},{"point":[13.36,19.7],"handleIn":[13.06,20.26],"handleOut":[13.67,19.15]},{"point":[14.89,19.15],"handleIn":[14.32,18.91],"handleOut":[15.46,19.38]},{"point":[15.62,20.64],"handleIn":[15.77,20.02],"handleOut":[15.47,21.26]},{"point":[14.3,21.6],"handleIn":[14.91,21.67]}]},{"name":"path","closed":false,"segments":[{"point":[13.68,20.71]},{"point":[13.68,21.35]},{"point":[13.01,21.15]}]},{"name":"path","closed":true,"segments":[{"point":[16,21.9]},{"point":[16,18.68]},{"point":[19.22,18.68]},{"point":[19.22,21.9]}]},{"name":"path","closed":false,"segments":[{"point":[16.92,20.29]},{"point":[18.3,20.29]}]},{"name":"path","closed":false,"segments":[{"point":[17.61,19.6]},{"point":[17.61,20.98]}]},{"name":"path","closed":true,"fill":"#c0c0c0","segments":[{"point":[2.2,21.9]},{"point":[29.8,21.9]},{"point":[29.8,24.2],"handleOut":[29.8,25.47]},{"point":[27.5,26.5],"handleIn":[28.77,26.5]},{"point":[4.5,26.5],"handleOut":[3.23,26.5]},{"point":[2.2,24.2],"handleIn":[2.2,25.47]}]},{"name":"path","closed":true,"segments":[{"point":[2.2,21.9]},{"point":[29.8,21.9]},{"point":[29.8,24.2],"handleOut":[29.8,25.47]},{"point":[27.5,26.5],"handleIn":[28.77,26.5]},{"point":[4.5,26.5],"handleOut":[3.23,26.5]},{"point":[2.2,24.2],"handleIn":[2.2,25.47]}]}]},{"childs":[{"name":"path","closed":true,"segments":[{"point":[2.2,26.5]},{"point":[2.2,3.5]},{"point":[29.8,3.5]},{"point":[29.8,26.5]}]},{"name":"path","closed":true,"segments":[{"point":[2.2,5.8],"handleOut":[2.2,4.53]},{"point":[4.5,3.5],"handleIn":[3.23,3.5]},{"point":[27.5,3.5],"handleOut":[28.77,3.5]},{"point":[29.8,5.8],"handleIn":[29.8,4.53]},{"point":[29.8,8.1]},{"point":[2.2,8.1]}]},{"name":"path","closed":true,"segments":[{"point":[2.2,5.8],"handleOut":[2.2,4.53]},{"point":[4.5,3.5],"handleIn":[3.23,3.5]},{"point":[27.5,3.5],"handleOut":[28.77,3.5]},{"point":[29.8,5.8],"handleIn":[29.8,4.53]},{"point":[29.8,8.1]},{"point":[2.2,8.1]}]},{"name":"path","closed":true,"segments":[{"point":[2.2,8.1]},{"point":[29.8,8.1]},{"point":[29.8,21.9]},{"point":[2.2,21.9]}]},{"name":"path","closed":true,"segments":[{"point":[2.2,8.1]},{"point":[29.8,8.1]},{"point":[29.8,21.9]},{"point":[2.2,21.9]}]},{"name":"path","closed":false,"segments":[{"point":[13.01,19.46]},{"point":[15.77,19.46]}]},{"name":"path","closed":false,"segments":[{"point":[13.01,20.29]},{"point":[15.77,20.29]}]},{"name":"path","closed":false,"segments":[{"point":[13.01,21.12]},{"point":[15.77,21.12]}]},{"name":"path","closed":true,"segments":[{"point":[16,21.9]},{"point":[16,18.68]},{"point":[19.22,18.68]},{"point":[19.22,21.9]}]},{"name":"path","closed":false,"segments":[{"point":[16.92,20.29]},{"point":[18.3,20.29]}]},{"name":"path","closed":false,"segments":[{"point":[17.61,19.6]},{"point":[17.61,20.98]}]},{"name":"path","closed":true,"fill":"#c0c0c0","segments":[{"point":[2.2,21.9]},{"point":[29.8,21.9]},{"point":[29.8,24.2],"handleOut":[29.8,25.47]},{"point":[27.5,26.5],"handleIn":[28.77,26.5]},{"point":[4.5,26.5],"handleOut":[3.23,26.5]},{"point":[2.2,24.2],"handleIn":[2.2,25.47]}]},{"name":"path","closed":true,"segments":[{"point":[2.2,21.9]},{"point":[29.8,21.9]},{"point":[29.8,24.2],"handleOut":[29.8,25.47]},{"point":[27.5,26.5],"handleIn":[28.77,26.5]},{"point":[4.5,26.5],"handleOut":[3.23,26.5]},{"point":[2.2,24.2],"handleIn":[2.2,25.47]}]}]},{"childs":[{"name":"path","closed":true,"segments":[{"point":[2.2,26.5]},{"point":[2.2,3.5]},{"point":[29.8,3.5]},{"point":[29.8,26.5]}]},{"name":"path","closed":true,"segments":[{"point":[2.2,5.8],"handleOut":[2.2,4.53]},{"point":[4.5,3.5],"handleIn":[3.23,3.5]},{"point":[27.5,3.5],"handleOut":[28.77,3.5]},{"point":[29.8,5.8],"handleIn":[29.8,4.53]},{"point":[29.8,8.1]},{"point":[2.2,8.1]}]},{"name":"path","closed":true,"segments":[{"point":[2.2,5.8],"handleOut":[2.2,4.53]},{"point":[4.5,3.5],"handleIn":[3.23,3.5]},{"point":[27.5,3.5],"handleOut":[28.77,3.5]},{"point":[29.8,5.8],"handleIn":[29.8,4.53]},{"point":[29.8,8.1]},{"point":[2.2,8.1]}]},{"name":"path","closed":true,"segments":[{"point":[2.2,8.1]},{"point":[29.8,8.1]},{"point":[29.8,21.9]},{"point":[2.2,21.9]}]},{"name":"path","closed":true,"segments":[{"point":[2.2,8.1]},{"point":[29.8,8.1]},{"point":[29.8,21.9]},{"point":[2.2,21.9]}]},{"name":"path","closed":false,"segments":[{"point":[13.56,18.91]},{"point":[13.56,21.67]}]},{"name":"path","closed":false,"segments":[{"point":[14.39,18.91]},{"point":[14.39,21.67]}]},{"name":"path","closed":false,"segments":[{"point":[15.22,18.91]},{"point":[15.22,21.67]}]},{"name":"path","closed":true,"segments":[{"point":[16,21.9]},{"point":[16,18.68]},{"point":[19.22,18.68]},{"point":[19.22,21.9]}]},{"name":"path","closed":false,"segments":[{"point":[16.92,20.29]},{"point":[18.3,20.29]}]},{"name":"path","closed":false,"segments":[{"point":[17.61,19.6]},{"point":[17.61,20.98]}]},{"name":"path","closed":true,"fill":"#c0c0c0","segments":[{"point":[2.2,21.9]},{"point":[29.8,21.9]},{"point":[29.8,24.2],"handleOut":[29.8,25.47]},{"point":[27.5,26.5],"handleIn":[28.77,26.5]},{"point":[4.5,26.5],"handleOut":[3.23,26.5]},{"point":[2.2,24.2],"handleIn":[2.2,25.47]}]},{"name":"path","closed":true,"segments":[{"point":[2.2,21.9]},{"point":[29.8,21.9]},{"point":[29.8,24.2],"handleOut":[29.8,25.47]},{"point":[27.5,26.5],"handleIn":[28.77,26.5]},{"point":[4.5,26.5],"handleOut":[3.23,26.5]},{"point":[2.2,24.2],"handleIn":[2.2,25.47]}]}]},{"childs":[{"name":"path","closed":true,"segments":[{"point":[1.6,27]},{"point":[1.6,3]},{"point":[30.400000000000002,3]},{"point":[30.400000000000002,27]}]},{"name":"path","closed":true,"fill":"#c0c0c0","segments":[{"point":[1.6,5.4],"handleOut":[1.6,4.07]},{"point":[4,3],"handleIn":[2.67,3]},{"point":[28,3],"handleOut":[29.33,3]},{"point":[30.4,5.4],"handleIn":[30.4,4.07]},{"point":[30.4,7.8]},{"point":[1.6,7.8]}]},{"name":"path","closed":true,"segments":[{"point":[1.6,5.4],"handleOut":[1.6,4.07]},{"point":[4,3],"handleIn":[2.67,3]},{"point":[28,3],"handleOut":[29.33,3]},{"point":[30.4,5.4],"handleIn":[30.4,4.07]},{"point":[30.4,7.8]},{"point":[1.6,7.8]}]},{"name":"path","closed":true,"segments":[{"point":[1.6,7.8]},{"point":[30.4,7.8]},{"point":[30.4,22.2]},{"point":[1.6,22.2]}]},{"name":"path","closed":true,"segments":[{"point":[1.6,7.8]},{"point":[30.4,7.8]},{"point":[30.4,22.2]},{"point":[1.6,22.2]}]},{"name":"path","closed":true,"segments":[{"point":[1.6,22.2]},{"point":[30.4,22.2]},{"point":[30.4,24.6],"handleOut":[30.4,25.93]},{"point":[28,27],"handleIn":[29.33,27]},{"point":[4,27],"handleOut":[2.67,27]},{"point":[1.6,24.6],"handleIn":[1.6,25.93]}]},{"name":"path","closed":true,"segments":[{"point":[1.6,22.2]},{"point":[30.4,22.2]},{"point":[30.4,24.6],"handleOut":[30.4,25.93]},{"point":[28,27],"handleIn":[29.33,27]},{"point":[4,27],"handleOut":[2.67,27]},{"point":[1.6,24.6],"handleIn":[1.6,25.93]}]}]},{"childs":[{"name":"path","closed":true,"segments":[{"point":[1.6,27]},{"point":[1.6,3]},{"point":[30.400000000000002,3]},{"point":[30.400000000000002,27]}]},{"name":"path","closed":true,"fill":"#c0c0c0","segments":[{"point":[1.6,5.4],"handleOut":[1.6,4.07]},{"point":[4,3],"handleIn":[2.67,3]},{"point":[28,3],"handleOut":[29.33,3]},{"point":[30.4,5.4],"handleIn":[30.4,4.07]},{"point":[30.4,7.8]},{"point":[1.6,7.8]}]},{"name":"path","closed":true,"segments":[{"point":[1.6,5.4],"handleOut":[1.6,4.07]},{"point":[4,3],"handleIn":[2.67,3]},{"point":[28,3],"handleOut":[29.33,3]},{"point":[30.4,5.4],"handleIn":[30.4,4.07]},{"point":[30.4,7.8]},{"point":[1.6,7.8]}]},{"name":"path","closed":true,"segments":[{"point":[1.6,7.8]},{"point":[30.4,7.8]},{"point":[30.4,22.2]},{"point":[1.6,22.2]}]},{"name":"path","closed":true,"segments":[{"point":[1.6,7.8]},{"point":[30.4,7.8]},{"point":[30.4,22.2]},{"point":[1.6,22.2]}]},{"name":"path","closed":false,"segments":[{"point":[15.26,21.62],"handleOut":[14.76,21.22]},{"point":[14.93,19.91],"handleIn":[14.61,20.48],"handleOut":[15.25,19.33]},{"point":[16.52,19.33],"handleIn":[15.92,19.08],"handleOut":[17.11,19.57]},{"point":[17.29,20.89],"handleIn":[17.44,20.24],"handleOut":[17.13,21.53]},{"point":[15.9,21.89],"handleIn":[16.54,21.96]}]},{"name":"path","closed":false,"segments":[{"point":[15.26,20.96]},{"point":[15.26,21.62]},{"point":[14.56,21.42]}]},{"name":"path","closed":true,"segments":[{"point":[1.6,22.2]},{"point":[30.4,22.2]},{"point":[30.4,24.6],"handleOut":[30.4,25.93]},{"point":[28,27],"handleIn":[29.33,27]},{"point":[4,27],"handleOut":[2.67,27]},{"point":[1.6,24.6],"handleIn":[1.6,25.93]}]},{"name":"path","closed":true,"segments":[{"point":[1.6,22.2]},{"point":[30.4,22.2]},{"point":[30.4,24.6],"handleOut":[30.4,25.93]},{"point":[28,27],"handleIn":[29.33,27]},{"point":[4,27],"handleOut":[2.67,27]},{"point":[1.6,24.6],"handleIn":[1.6,25.93]}]}]},{"childs":[{"name":"path","closed":true,"segments":[{"point":[1.6,27]},{"point":[1.6,3]},{"point":[30.400000000000002,3]},{"point":[30.400000000000002,27]}]},{"name":"path","closed":true,"fill":"#c0c0c0","segments":[{"point":[1.6,5.4],"handleOut":[1.6,4.07]},{"point":[4,3],"handleIn":[2.67,3]},{"point":[28,3],"handleOut":[29.33,3]},{"point":[30.4,5.4],"handleIn":[30.4,4.07]},{"point":[30.4,7.8]},{"point":[1.6,7.8]}]},{"name":"path","closed":true,"segments":[{"point":[1.6,5.4],"handleOut":[1.6,4.07]},{"point":[4,3],"handleIn":[2.67,3]},{"point":[28,3],"handleOut":[29.33,3]},{"point":[30.4,5.4],"handleIn":[30.4,4.07]},{"point":[30.4,7.8]},{"point":[1.6,7.8]}]},{"name":"path","closed":true,"segments":[{"point":[1.6,7.8]},{"point":[30.4,7.8]},{"point":[30.4,22.2]},{"point":[1.6,22.2]}]},{"name":"path","closed":true,"segments":[{"point":[1.6,7.8]},{"point":[30.4,7.8]},{"point":[30.4,22.2]},{"point":[1.6,22.2]}]},{"name":"path","closed":false,"segments":[{"point":[14.56,19.66]},{"point":[17.44,19.66]}]},{"name":"path","closed":false,"segments":[{"point":[14.56,20.52]},{"point":[17.44,20.52]}]},{"name":"path","closed":false,"segments":[{"point":[14.56,21.38]},{"point":[17.44,21.38]}]},{"name":"path","closed":true,"segments":[{"point":[1.6,22.2]},{"point":[30.4,22.2]},{"point":[30.4,24.6],"handleOut":[30.4,25.93]},{"point":[28,27],"handleIn":[29.33,27]},{"point":[4,27],"handleOut":[2.67,27]},{"point":[1.6,24.6],"handleIn":[1.6,25.93]}]},{"name":"path","closed":true,"segments":[{"point":[1.6,22.2]},{"point":[30.4,22.2]},{"point":[30.4,24.6],"handleOut":[30.4,25.93]},{"point":[28,27],"handleIn":[29.33,27]},{"point":[4,27],"handleOut":[2.67,27]},{"point":[1.6,24.6],"handleIn":[1.6,25.93]}]}]},{"childs":[{"name":"path","closed":true,"segments":[{"point":[1.6,27]},{"point":[1.6,3]},{"point":[30.400000000000002,3]},{"point":[30.400000000000002,27]}]},{"name":"path","closed":true,"fill":"#c0c0c0","segments":[{"point":[1.6,5.4],"handleOut":[1.6,4.07]},{"point":[4,3],"handleIn":[2.67,3]},{"point":[28,3],"handleOut":[29.33,3]},{"point":[30.4,5.4],"handleIn":[30.4,4.07]},{"point":[30.4,7.8]},{"point":[1.6,7.8]}]},{"name":"path","closed":true,"segments":[{"point":[1.6,5.4],"handleOut":[1.6,4.07]},{"point":[4,3],"handleIn":[2.67,3]},{"point":[28,3],"handleOut":[29.33,3]},{"point":[30.4,5.4],"handleIn":[30.4,4.07]},{"point":[30.4,7.8]},{"point":[1.6,7.8]}]},{"name":"path","closed":true,"segments":[{"point":[1.6,7.8]},{"point":[30.4,7.8]},{"point":[30.4,22.2]},{"point":[1.6,22.2]}]},{"name":"path","closed":true,"segments":[{"point":[1.6,7.8]},{"point":[30.4,7.8]},{"point":[30.4,22.2]},{"point":[1.6,22.2]}]},{"name":"path","closed":false,"segments":[{"point":[15.14,19.08]},{"point":[15.14,21.96]}]},{"name":"path","closed":false,"segments":[{"point":[16,19.08]},{"point":[16,21.96]}]},{"name":"path","closed":false,"segments":[{"point":[16.86,19.08]},{"point":[16.86,21.96]}]},{"name":"path","closed":true,"segments":[{"point":[1.6,22.2]},{"point":[30.4,22.2]},{"point":[30.4,24.6],"handleOut":[30.4,25.93]},{"point":[28,27],"handleIn":[29.33,27]},{"point":[4,27],"handleOut":[2.67,27]},{"point":[1.6,24.6],"handleIn":[1.6,25.93]}]},{"name":"path","closed":true,"segments":[{"point":[1.6,22.2]},{"point":[30.4,22.2]},{"point":[30.4,24.6],"handleOut":[30.4,25.93]},{"point":[28,27],"handleIn":[29.33,27]},{"point":[4,27],"handleOut":[2.67,27]},{"point":[1.6,24.6],"handleIn":[1.6,25.93]}]}]},{"childs":[{"name":"path","closed":true,"segments":[{"point":[1.6,27]},{"point":[1.6,3]},{"point":[30.400000000000002,3]},{"point":[30.400000000000002,27]}]},{"name":"path","closed":true,"fill":"#c0c0c0","segments":[{"point":[1.6,5.4],"handleOut":[1.6,4.07]},{"point":[4,3],"handleIn":[2.67,3]},{"point":[28,3],"handleOut":[29.33,3]},{"point":[30.4,5.4],"handleIn":[30.4,4.07]},{"point":[30.4,7.8]},{"point":[1.6,7.8]}]},{"name":"path","closed":true,"segments":[{"point":[1.6,5.4],"handleOut":[1.6,4.07]},{"point":[4,3],"handleIn":[2.67,3]},{"point":[28,3],"handleOut":[29.33,3]},{"point":[30.4,5.4],"handleIn":[30.4,4.07]},{"point":[30.4,7.8]},{"point":[1.6,7.8]}]},{"name":"path","closed":true,"segments":[{"point":[1.6,7.8]},{"point":[30.4,7.8]},{"point":[30.4,22.2]},{"point":[1.6,22.2]}]},{"name":"path","closed":true,"segments":[{"point":[1.6,7.8]},{"point":[30.4,7.8]},{"point":[30.4,22.2]},{"point":[1.6,22.2]}]},{"name":"path","closed":true,"segments":[{"point":[14.32,22.2]},{"point":[14.32,18.84]},{"point":[17.68,18.84]},{"point":[17.68,22.2]}]},{"name":"path","closed":false,"segments":[{"point":[15.28,20.52]},{"point":[16.72,20.52]}]},{"name":"path","closed":false,"segments":[{"point":[16,19.8]},{"point":[16,21.24]}]},{"name":"path","closed":true,"segments":[{"point":[1.6,22.2]},{"point":[30.4,22.2]},{"point":[30.4,24.6],"handleOut":[30.4,25.93]},{"point":[28,27],"handleIn":[29.33,27]},{"point":[4,27],"handleOut":[2.67,27]},{"point":[1.6,24.6],"handleIn":[1.6,25.93]}]},{"name":"path","closed":true,"segments":[{"point":[1.6,22.2]},{"point":[30.4,22.2]},{"point":[30.4,24.6],"handleOut":[30.4,25.93]},{"point":[28,27],"handleIn":[29.33,27]},{"point":[4,27],"handleOut":[2.67,27]},{"point":[1.6,24.6],"handleIn":[1.6,25.93]}]}]},{"childs":[{"name":"path","closed":true,"segments":[{"point":[1.6,27]},{"point":[1.6,3]},{"point":[30.400000000000002,3]},{"point":[30.400000000000002,27]}]},{"name":"path","closed":true,"fill":"#c0c0c0","segments":[{"point":[1.6,5.4],"handleOut":[1.6,4.07]},{"point":[4,3],"handleIn":[2.67,3]},{"point":[28,3],"handleOut":[29.33,3]},{"point":[30.4,5.4],"handleIn":[30.4,4.07]},{"point":[30.4,7.8]},{"point":[1.6,7.8]}]},{"name":"path","closed":true,"segments":[{"point":[1.6,5.4],"handleOut":[1.6,4.07]},{"point":[4,3],"handleIn":[2.67,3]},{"point":[28,3],"handleOut":[29.33,3]},{"point":[30.4,5.4],"handleIn":[30.4,4.07]},{"point":[30.4,7.8]},{"point":[1.6,7.8]}]},{"name":"path","closed":true,"segments":[{"point":[1.6,7.8]},{"point":[30.4,7.8]},{"point":[30.4,22.2]},{"point":[1.6,22.2]}]},{"name":"path","closed":true,"segments":[{"point":[1.6,7.8]},{"point":[30.4,7.8]},{"point":[30.4,22.2]},{"point":[1.6,22.2]}]},{"name":"path","closed":false,"segments":[{"point":[13.58,21.62],"handleOut":[13.08,21.22]},{"point":[13.25,19.91],"handleIn":[12.93,20.48],"handleOut":[13.57,19.33]},{"point":[14.84,19.33],"handleIn":[14.24,19.08],"handleOut":[15.43,19.57]},{"point":[15.61,20.89],"handleIn":[15.76,20.24],"handleOut":[15.45,21.53]},{"point":[14.22,21.89],"handleIn":[14.86,21.96]}]},{"name":"path","closed":false,"segments":[{"point":[13.58,20.96]},{"point":[13.58,21.62]},{"point":[12.88,21.42]}]},{"name":"path","closed":true,"segments":[{"point":[16,22.2]},{"point":[16,18.84]},{"point":[19.36,18.84]},{"point":[19.36,22.2]}]},{"name":"path","closed":false,"segments":[{"point":[16.96,20.52]},{"point":[18.4,20.52]}]},{"name":"path","closed":false,"segments":[{"point":[17.68,19.8]},{"point":[17.68,21.24]}]},{"name":"path","closed":true,"segments":[{"point":[1.6,22.2]},{"point":[30.4,22.2]},{"point":[30.4,24.6],"handleOut":[30.4,25.93]},{"point":[28,27],"handleIn":[29.33,27]},{"point":[4,27],"handleOut":[2.67,27]},{"point":[1.6,24.6],"handleIn":[1.6,25.93]}]},{"name":"path","closed":true,"segments":[{"point":[1.6,22.2]},{"point":[30.4,22.2]},{"point":[30.4,24.6],"handleOut":[30.4,25.93]},{"point":[28,27],"handleIn":[29.33,27]},{"point":[4,27],"handleOut":[2.67,27]},{"point":[1.6,24.6],"handleIn":[1.6,25.93]}]}]},{"childs":[{"name":"path","closed":true,"segments":[{"point":[1.6,27]},{"point":[1.6,3]},{"point":[30.400000000000002,3]},{"point":[30.400000000000002,27]}]},{"name":"path","closed":true,"fill":"#c0c0c0","segments":[{"point":[1.6,5.4],"handleOut":[1.6,4.07]},{"point":[4,3],"handleIn":[2.67,3]},{"point":[28,3],"handleOut":[29.33,3]},{"point":[30.4,5.4],"handleIn":[30.4,4.07]},{"point":[30.4,7.8]},{"point":[1.6,7.8]}]},{"name":"path","closed":true,"segments":[{"point":[1.6,5.4],"handleOut":[1.6,4.07]},{"point":[4,3],"handleIn":[2.67,3]},{"point":[28,3],"handleOut":[29.33,3]},{"point":[30.4,5.4],"handleIn":[30.4,4.07]},{"point":[30.4,7.8]},{"point":[1.6,7.8]}]},{"name":"path","closed":true,"segments":[{"point":[1.6,7.8]},{"point":[30.4,7.8]},{"point":[30.4,22.2]},{"point":[1.6,22.2]}]},{"name":"path","closed":true,"segments":[{"point":[1.6,7.8]},{"point":[30.4,7.8]},{"point":[30.4,22.2]},{"point":[1.6,22.2]}]},{"name":"path","closed":false,"segments":[{"point":[12.88,19.66]},{"point":[15.76,19.66]}]},{"name":"path","closed":false,"segments":[{"point":[12.88,20.52]},{"point":[15.76,20.52]}]},{"name":"path","closed":false,"segments":[{"point":[12.88,21.38]},{"point":[15.76,21.38]}]},{"name":"path","closed":true,"segments":[{"point":[16,22.2]},{"point":[16,18.84]},{"point":[19.36,18.84]},{"point":[19.36,22.2]}]},{"name":"path","closed":false,"segments":[{"point":[16.96,20.52]},{"point":[18.4,20.52]}]},{"name":"path","closed":false,"segments":[{"point":[17.68,19.8]},{"point":[17.68,21.24]}]},{"name":"path","closed":true,"segments":[{"point":[1.6,22.2]},{"point":[30.4,22.2]},{"point":[30.4,24.6],"handleOut":[30.4,25.93]},{"point":[28,27],"handleIn":[29.33,27]},{"point":[4,27],"handleOut":[2.67,27]},{"point":[1.6,24.6],"handleIn":[1.6,25.93]}]},{"name":"path","closed":true,"segments":[{"point":[1.6,22.2]},{"point":[30.4,22.2]},{"point":[30.4,24.6],"handleOut":[30.4,25.93]},{"point":[28,27],"handleIn":[29.33,27]},{"point":[4,27],"handleOut":[2.67,27]},{"point":[1.6,24.6],"handleIn":[1.6,25.93]}]}]},{"childs":[{"name":"path","closed":true,"segments":[{"point":[1.6,27]},{"point":[1.6,3]},{"point":[30.400000000000002,3]},{"point":[30.400000000000002,27]}]},{"name":"path","closed":true,"fill":"#c0c0c0","segments":[{"point":[1.6,5.4],"handleOut":[1.6,4.07]},{"point":[4,3],"handleIn":[2.67,3]},{"point":[28,3],"handleOut":[29.33,3]},{"point":[30.4,5.4],"handleIn":[30.4,4.07]},{"point":[30.4,7.8]},{"point":[1.6,7.8]}]},{"name":"path","closed":true,"segments":[{"point":[1.6,5.4],"handleOut":[1.6,4.07]},{"point":[4,3],"handleIn":[2.67,3]},{"point":[28,3],"handleOut":[29.33,3]},{"point":[30.4,5.4],"handleIn":[30.4,4.07]},{"point":[30.4,7.8]},{"point":[1.6,7.8]}]},{"name":"path","closed":true,"segments":[{"point":[1.6,7.8]},{"point":[30.4,7.8]},{"point":[30.4,22.2]},{"point":[1.6,22.2]}]},{"name":"path","closed":true,"segments":[{"point":[1.6,7.8]},{"point":[30.4,7.8]},{"point":[30.4,22.2]},{"point":[1.6,22.2]}]},{"name":"path","closed":false,"segments":[{"point":[13.46,19.08]},{"point":[13.46,21.96]}]},{"name":"path","closed":false,"segments":[{"point":[14.32,19.08]},{"point":[14.32,21.96]}]},{"name":"path","closed":false,"segments":[{"point":[15.18,19.08]},{"point":[15.18,21.96]}]},{"name":"path","closed":true,"segments":[{"point":[16,22.2]},{"point":[16,18.84]},{"point":[19.36,18.84]},{"point":[19.36,22.2]}]},{"name":"path","closed":false,"segments":[{"point":[16.96,20.52]},{"point":[18.4,20.52]}]},{"name":"path","closed":false,"segments":[{"point":[17.68,19.8]},{"point":[17.68,21.24]}]},{"name":"path","closed":true,"segments":[{"point":[1.6,22.2]},{"point":[30.4,22.2]},{"point":[30.4,24.6],"handleOut":[30.4,25.93]},{"point":[28,27],"handleIn":[29.33,27]},{"point":[4,27],"handleOut":[2.67,27]},{"point":[1.6,24.6],"handleIn":[1.6,25.93]}]},{"name":"path","closed":true,"segments":[{"point":[1.6,22.2]},{"point":[30.4,22.2]},{"point":[30.4,24.6],"handleOut":[30.4,25.93]},{"point":[28,27],"handleIn":[29.33,27]},{"point":[4,27],"handleOut":[2.67,27]},{"point":[1.6,24.6],"handleIn":[1.6,25.93]}]}]},{"childs":[{"name":"path","closed":true,"segments":[{"point":[2,22]},{"point":[2,8]},{"point":[30,8]},{"point":[30,22]}]},{"name":"path","closed":true,"fill":"#c0c0c0","segments":[{"point":[2,8.7],"handleOut":[2,8.31]},{"point":[2.7,8],"handleIn":[2.31,8]},{"point":[29.3,8],"handleOut":[29.69,8]},{"point":[30,8.7],"handleIn":[30,8.31]},{"point":[30,9.4]},{"point":[2,9.4]}]},{"name":"path","closed":true,"segments":[{"point":[2,8.7],"handleOut":[2,8.31]},{"point":[2.7,8],"handleIn":[2.31,8]},{"point":[29.3,8],"handleOut":[29.69,8]},{"point":[30,8.7],"handleIn":[30,8.31]},{"point":[30,9.4]},{"point":[2,9.4]}]},{"name":"path","closed":true,"segments":[{"point":[2,9.4]},{"point":[30,9.4]},{"point":[30,20.6]},{"point":[2,20.6]}]},{"name":"path","closed":true,"segments":[{"point":[2,9.4]},{"point":[30,9.4]},{"point":[30,20.6]},{"point":[2,20.6]}]},{"name":"path","closed":true,"segments":[{"point":[2,20.6]},{"point":[30,20.6]},{"point":[30,21.3],"handleOut":[30,21.69]},{"point":[29.3,22],"handleIn":[29.69,22]},{"point":[2.7,22],"handleOut":[2.31,22]},{"point":[2,21.3],"handleIn":[2,21.69]}]},{"name":"path","closed":true,"segments":[{"point":[2,20.6]},{"point":[30,20.6]},{"point":[30,21.3],"handleOut":[30,21.69]},{"point":[29.3,22],"handleIn":[29.69,22]},{"point":[2.7,22],"handleOut":[2.31,22]},{"point":[2,21.3],"handleIn":[2,21.69]}]}]},{"childs":[{"name":"path","closed":true,"segments":[{"point":[2.2,26.5]},{"point":[2.2,3.5]},{"point":[29.8,3.5]},{"point":[29.8,26.5]}]},{"name":"path","closed":true,"fill":"#c0c0c0","segments":[{"point":[2.2,5.8],"handleOut":[2.2,4.53]},{"point":[4.5,3.5],"handleIn":[3.23,3.5]},{"point":[27.5,3.5],"handleOut":[28.77,3.5]},{"point":[29.8,5.8],"handleIn":[29.8,4.53]},{"point":[29.8,8.1]},{"point":[2.2,8.1]}]},{"name":"path","closed":true,"segments":[{"point":[2.2,5.8],"handleOut":[2.2,4.53]},{"point":[4.5,3.5],"handleIn":[3.23,3.5]},{"point":[27.5,3.5],"handleOut":[28.77,3.5]},{"point":[29.8,5.8],"handleIn":[29.8,4.53]},{"point":[29.8,8.1]},{"point":[2.2,8.1]}]},{"name":"path","closed":true,"segments":[{"point":[2.2,8.1]},{"point":[29.8,8.1]},{"point":[29.8,21.9]},{"point":[2.2,21.9]}]},{"name":"path","closed":true,"segments":[{"point":[2.2,8.1]},{"point":[29.8,8.1]},{"point":[29.8,21.9]},{"point":[2.2,21.9]}]},{"name":"path","closed":true,"segments":[{"point":[2.2,21.9]},{"point":[29.8,21.9]},{"point":[29.8,24.2],"handleOut":[29.8,25.47]},{"point":[27.5,26.5],"handleIn":[28.77,26.5]},{"point":[4.5,26.5],"handleOut":[3.23,26.5]},{"point":[2.2,24.2],"handleIn":[2.2,25.47]}]},{"name":"path","closed":true,"segments":[{"point":[2.2,21.9]},{"point":[29.8,21.9]},{"point":[29.8,24.2],"handleOut":[29.8,25.47]},{"point":[27.5,26.5],"handleIn":[28.77,26.5]},{"point":[4.5,26.5],"handleOut":[3.23,26.5]},{"point":[2.2,24.2],"handleIn":[2.2,25.47]}]}]},{"childs":[{"name":"path","closed":true,"segments":[{"point":[2.2,26.5]},{"point":[2.2,3.5]},{"point":[29.8,3.5]},{"point":[29.8,26.5]}]},{"name":"path","closed":true,"segments":[{"point":[2.2,5.8],"handleOut":[2.2,4.53]},{"point":[4.5,3.5],"handleIn":[3.23,3.5]},{"point":[27.5,3.5],"handleOut":[28.77,3.5]},{"point":[29.8,5.8],"handleIn":[29.8,4.53]},{"point":[29.8,8.1]},{"point":[2.2,8.1]}]},{"name":"path","closed":true,"segments":[{"point":[2.2,5.8],"handleOut":[2.2,4.53]},{"point":[4.5,3.5],"handleIn":[3.23,3.5]},{"point":[27.5,3.5],"handleOut":[28.77,3.5]},{"point":[29.8,5.8],"handleIn":[29.8,4.53]},{"point":[29.8,8.1]},{"point":[2.2,8.1]}]},{"name":"path","closed":true,"segments":[{"point":[2.2,8.1]},{"point":[29.8,8.1]},{"point":[29.8,21.9]},{"point":[2.2,21.9]}]},{"name":"path","closed":true,"segments":[{"point":[2.2,8.1]},{"point":[29.8,8.1]},{"point":[29.8,21.9]},{"point":[2.2,21.9]}]},{"name":"path","closed":false,"segments":[{"point":[15.29,21.35],"handleOut":[14.81,20.96]},{"point":[14.97,19.7],"handleIn":[14.67,20.26],"handleOut":[15.28,19.15]},{"point":[16.5,19.15],"handleIn":[15.93,18.91],"handleOut":[17.07,19.38]},{"point":[17.23,20.64],"handleIn":[17.38,20.02],"handleOut":[17.08,21.26]},{"point":[15.91,21.6],"handleIn":[16.52,21.67]}]},{"name":"path","closed":false,"segments":[{"point":[15.29,20.71]},{"point":[15.29,21.35]},{"point":[14.62,21.15]}]},{"name":"path","closed":true,"fill":"#c0c0c0","segments":[{"point":[2.2,21.9]},{"point":[29.8,21.9]},{"point":[29.8,24.2],"handleOut":[29.8,25.47]},{"point":[27.5,26.5],"handleIn":[28.77,26.5]},{"point":[4.5,26.5],"handleOut":[3.23,26.5]},{"point":[2.2,24.2],"handleIn":[2.2,25.47]}]},{"name":"path","closed":true,"segments":[{"point":[2.2,21.9]},{"point":[29.8,21.9]},{"point":[29.8,24.2],"handleOut":[29.8,25.47]},{"point":[27.5,26.5],"handleIn":[28.77,26.5]},{"point":[4.5,26.5],"handleOut":[3.23,26.5]},{"point":[2.2,24.2],"handleIn":[2.2,25.47]}]}]},{"childs":[{"name":"path","closed":true,"segments":[{"point":[2.2,26.5]},{"point":[2.2,3.5]},{"point":[29.8,3.5]},{"point":[29.8,26.5]}]},{"name":"path","closed":true,"fill":"#c0c0c0","segments":[{"point":[2.2,5.8],"handleOut":[2.2,4.53]},{"point":[4.5,3.5],"handleIn":[3.23,3.5]},{"point":[27.5,3.5],"handleOut":[28.77,3.5]},{"point":[29.8,5.8],"handleIn":[29.8,4.53]},{"point":[29.8,8.1]},{"point":[2.2,8.1]}]},{"name":"path","closed":true,"segments":[{"point":[2.2,5.8],"handleOut":[2.2,4.53]},{"point":[4.5,3.5],"handleIn":[3.23,3.5]},{"point":[27.5,3.5],"handleOut":[28.77,3.5]},{"point":[29.8,5.8],"handleIn":[29.8,4.53]},{"point":[29.8,8.1]},{"point":[2.2,8.1]}]},{"name":"path","closed":true,"segments":[{"point":[2.2,8.1]},{"point":[29.8,8.1]},{"point":[29.8,21.9]},{"point":[2.2,21.9]}]},{"name":"path","closed":true,"segments":[{"point":[2.2,8.1]},{"point":[29.8,8.1]},{"point":[29.8,21.9]},{"point":[2.2,21.9]}]},{"name":"path","closed":false,"segments":[{"point":[14.62,19.46]},{"point":[17.38,19.46]}]},{"name":"path","closed":false,"segments":[{"point":[14.62,20.29]},{"point":[17.38,20.29]}]},{"name":"path","closed":false,"segments":[{"point":[14.62,21.12]},{"point":[17.38,21.12]}]},{"name":"path","closed":true,"segments":[{"point":[2.2,21.9]},{"point":[29.8,21.9]},{"point":[29.8,24.2],"handleOut":[29.8,25.47]},{"point":[27.5,26.5],"handleIn":[28.77,26.5]},{"point":[4.5,26.5],"handleOut":[3.23,26.5]},{"point":[2.2,24.2],"handleIn":[2.2,25.47]}]},{"name":"path","closed":true,"segments":[{"point":[2.2,21.9]},{"point":[29.8,21.9]},{"point":[29.8,24.2],"handleOut":[29.8,25.47]},{"point":[27.5,26.5],"handleIn":[28.77,26.5]},{"point":[4.5,26.5],"handleOut":[3.23,26.5]},{"point":[2.2,24.2],"handleIn":[2.2,25.47]}]}]},{"childs":[{"name":"path","closed":true,"segments":[{"point":[2.2,26.5]},{"point":[2.2,3.5]},{"point":[29.8,3.5]},{"point":[29.8,26.5]}]},{"name":"path","closed":true,"fill":"#c0c0c0","segments":[{"point":[2.2,5.8],"handleOut":[2.2,4.53]},{"point":[4.5,3.5],"handleIn":[3.23,3.5]},{"point":[27.5,3.5],"handleOut":[28.77,3.5]},{"point":[29.8,5.8],"handleIn":[29.8,4.53]},{"point":[29.8,8.1]},{"point":[2.2,8.1]}]},{"name":"path","closed":true,"segments":[{"point":[2.2,5.8],"handleOut":[2.2,4.53]},{"point":[4.5,3.5],"handleIn":[3.23,3.5]},{"point":[27.5,3.5],"handleOut":[28.77,3.5]},{"point":[29.8,5.8],"handleIn":[29.8,4.53]},{"point":[29.8,8.1]},{"point":[2.2,8.1]}]},{"name":"path","closed":true,"segments":[{"point":[2.2,8.1]},{"point":[29.8,8.1]},{"point":[29.8,21.9]},{"point":[2.2,21.9]}]},{"name":"path","closed":true,"segments":[{"point":[2.2,8.1]},{"point":[29.8,8.1]},{"point":[29.8,21.9]},{"point":[2.2,21.9]}]},{"name":"path","closed":false,"segments":[{"point":[15.17,18.91]},{"point":[15.17,21.67]}]},{"name":"path","closed":false,"segments":[{"point":[16,18.91]},{"point":[16,21.67]}]},{"name":"path","closed":false,"segments":[{"point":[16.83,18.91]},{"point":[16.83,21.67]}]},{"name":"path","closed":true,"segments":[{"point":[2.2,21.9]},{"point":[29.8,21.9]},{"point":[29.8,24.2],"handleOut":[29.8,25.47]},{"point":[27.5,26.5],"handleIn":[28.77,26.5]},{"point":[4.5,26.5],"handleOut":[3.23,26.5]},{"point":[2.2,24.2],"handleIn":[2.2,25.47]}]},{"name":"path","closed":true,"segments":[{"point":[2.2,21.9]},{"point":[29.8,21.9]},{"point":[29.8,24.2],"handleOut":[29.8,25.47]},{"point":[27.5,26.5],"handleIn":[28.77,26.5]},{"point":[4.5,26.5],"handleOut":[3.23,26.5]},{"point":[2.2,24.2],"handleIn":[2.2,25.47]}]}]},{"childs":[{"name":"path","closed":true,"segments":[{"point":[2.2,26.5]},{"point":[2.2,3.5]},{"point":[29.8,3.5]},{"point":[29.8,26.5]}]},{"name":"path","closed":true,"fill":"#c0c0c0","segments":[{"point":[2.2,5.8],"handleOut":[2.2,4.53]},{"point":[4.5,3.5],"handleIn":[3.23,3.5]},{"point":[27.5,3.5],"handleOut":[28.77,3.5]},{"point":[29.8,5.8],"handleIn":[29.8,4.53]},{"point":[29.8,8.1]},{"point":[2.2,8.1]}]},{"name":"path","closed":true,"segments":[{"point":[2.2,5.8],"handleOut":[2.2,4.53]},{"point":[4.5,3.5],"handleIn":[3.23,3.5]},{"point":[27.5,3.5],"handleOut":[28.77,3.5]},{"point":[29.8,5.8],"handleIn":[29.8,4.53]},{"point":[29.8,8.1]},{"point":[2.2,8.1]}]},{"name":"path","closed":true,"segments":[{"point":[2.2,8.1]},{"point":[29.8,8.1]},{"point":[29.8,21.9]},{"point":[2.2,21.9]}]},{"name":"path","closed":true,"segments":[{"point":[2.2,8.1]},{"point":[29.8,8.1]},{"point":[29.8,21.9]},{"point":[2.2,21.9]}]},{"name":"path","closed":true,"segments":[{"point":[14.39,21.9]},{"point":[14.39,18.68]},{"point":[17.61,18.68]},{"point":[17.61,21.9]}]},{"name":"path","closed":false,"segments":[{"point":[15.31,20.29]},{"point":[16.69,20.29]}]},{"name":"path","closed":false,"segments":[{"point":[16,19.6]},{"point":[16,20.98]}]},{"name":"path","closed":true,"segments":[{"point":[2.2,21.9]},{"point":[29.8,21.9]},{"point":[29.8,24.2],"handleOut":[29.8,25.47]},{"point":[27.5,26.5],"handleIn":[28.77,26.5]},{"point":[4.5,26.5],"handleOut":[3.23,26.5]},{"point":[2.2,24.2],"handleIn":[2.2,25.47]}]},{"name":"path","closed":true,"segments":[{"point":[2.2,21.9]},{"point":[29.8,21.9]},{"point":[29.8,24.2],"handleOut":[29.8,25.47]},{"point":[27.5,26.5],"handleIn":[28.77,26.5]},{"point":[4.5,26.5],"handleOut":[3.23,26.5]},{"point":[2.2,24.2],"handleIn":[2.2,25.47]}]}]},{"childs":[{"name":"path","closed":true,"segments":[{"point":[2.2,26.5]},{"point":[2.2,3.5]},{"point":[29.8,3.5]},{"point":[29.8,26.5]}]},{"name":"path","closed":true,"fill":"#c0c0c0","segments":[{"point":[2.2,5.8],"handleOut":[2.2,4.53]},{"point":[4.5,3.5],"handleIn":[3.23,3.5]},{"point":[27.5,3.5],"handleOut":[28.77,3.5]},{"point":[29.8,5.8],"handleIn":[29.8,4.53]},{"point":[29.8,8.1]},{"point":[2.2,8.1]}]},{"name":"path","closed":true,"segments":[{"point":[2.2,5.8],"handleOut":[2.2,4.53]},{"point":[4.5,3.5],"handleIn":[3.23,3.5]},{"point":[27.5,3.5],"handleOut":[28.77,3.5]},{"point":[29.8,5.8],"handleIn":[29.8,4.53]},{"point":[29.8,8.1]},{"point":[2.2,8.1]}]},{"name":"path","closed":true,"segments":[{"point":[2.2,8.1]},{"point":[29.8,8.1]},{"point":[29.8,21.9]},{"point":[2.2,21.9]}]},{"name":"path","closed":true,"segments":[{"point":[2.2,8.1]},{"point":[29.8,8.1]},{"point":[29.8,21.9]},{"point":[2.2,21.9]}]},{"name":"path","closed":false,"segments":[{"point":[13.68,21.35],"handleOut":[13.2,20.96]},{"point":[13.36,19.7],"handleIn":[13.06,20.26],"handleOut":[13.67,19.15]},{"point":[14.89,19.15],"handleIn":[14.32,18.91],"handleOut":[15.46,19.38]},{"point":[15.62,20.64],"handleIn":[15.77,20.02],"handleOut":[15.47,21.26]},{"point":[14.3,21.6],"handleIn":[14.91,21.67]}]},{"name":"path","closed":false,"segments":[{"point":[13.68,20.71]},{"point":[13.68,21.35]},{"point":[13.01,21.15]}]},{"name":"path","closed":true,"segments":[{"point":[16,21.9]},{"point":[16,18.68]},{"point":[19.22,18.68]},{"point":[19.22,21.9]}]},{"name":"path","closed":false,"segments":[{"point":[16.92,20.29]},{"point":[18.3,20.29]}]},{"name":"path","closed":false,"segments":[{"point":[17.61,19.6]},{"point":[17.61,20.98]}]},{"name":"path","closed":true,"segments":[{"point":[2.2,21.9]},{"point":[29.8,21.9]},{"point":[29.8,24.2],"handleOut":[29.8,25.47]},{"point":[27.5,26.5],"handleIn":[28.77,26.5]},{"point":[4.5,26.5],"handleOut":[3.23,26.5]},{"point":[2.2,24.2],"handleIn":[2.2,25.47]}]},{"name":"path","closed":true,"segments":[{"point":[2.2,21.9]},{"point":[29.8,21.9]},{"point":[29.8,24.2],"handleOut":[29.8,25.47]},{"point":[27.5,26.5],"handleIn":[28.77,26.5]},{"point":[4.5,26.5],"handleOut":[3.23,26.5]},{"point":[2.2,24.2],"handleIn":[2.2,25.47]}]}]},{"childs":[{"name":"path","closed":true,"segments":[{"point":[2.2,26.5]},{"point":[2.2,3.5]},{"point":[29.8,3.5]},{"point":[29.8,26.5]}]},{"name":"path","closed":true,"fill":"#c0c0c0","segments":[{"point":[2.2,5.8],"handleOut":[2.2,4.53]},{"point":[4.5,3.5],"handleIn":[3.23,3.5]},{"point":[27.5,3.5],"handleOut":[28.77,3.5]},{"point":[29.8,5.8],"handleIn":[29.8,4.53]},{"point":[29.8,8.1]},{"point":[2.2,8.1]}]},{"name":"path","closed":true,"segments":[{"point":[2.2,5.8],"handleOut":[2.2,4.53]},{"point":[4.5,3.5],"handleIn":[3.23,3.5]},{"point":[27.5,3.5],"handleOut":[28.77,3.5]},{"point":[29.8,5.8],"handleIn":[29.8,4.53]},{"point":[29.8,8.1]},{"point":[2.2,8.1]}]},{"name":"path","closed":true,"segments":[{"point":[2.2,8.1]},{"point":[29.8,8.1]},{"point":[29.8,21.9]},{"point":[2.2,21.9]}]},{"name":"path","closed":true,"segments":[{"point":[2.2,8.1]},{"point":[29.8,8.1]},{"point":[29.8,21.9]},{"point":[2.2,21.9]}]},{"name":"path","closed":false,"segments":[{"point":[13.01,19.46]},{"point":[15.77,19.46]}]},{"name":"path","closed":false,"segments":[{"point":[13.01,20.29]},{"point":[15.77,20.29]}]},{"name":"path","closed":false,"segments":[{"point":[13.01,21.12]},{"point":[15.77,21.12]}]},{"name":"path","closed":true,"segments":[{"point":[16,21.9]},{"point":[16,18.68]},{"point":[19.22,18.68]},{"point":[19.22,21.9]}]},{"name":"path","closed":false,"segments":[{"point":[16.92,20.29]},{"point":[18.3,20.29]}]},{"name":"path","closed":false,"segments":[{"point":[17.61,19.6]},{"point":[17.61,20.98]}]},{"name":"path","closed":true,"segments":[{"point":[2.2,21.9]},{"point":[29.8,21.9]},{"point":[29.8,24.2],"handleOut":[29.8,25.47]},{"point":[27.5,26.5],"handleIn":[28.77,26.5]},{"point":[4.5,26.5],"handleOut":[3.23,26.5]},{"point":[2.2,24.2],"handleIn":[2.2,25.47]}]},{"name":"path","closed":true,"segments":[{"point":[2.2,21.9]},{"point":[29.8,21.9]},{"point":[29.8,24.2],"handleOut":[29.8,25.47]},{"point":[27.5,26.5],"handleIn":[28.77,26.5]},{"point":[4.5,26.5],"handleOut":[3.23,26.5]},{"point":[2.2,24.2],"handleIn":[2.2,25.47]}]}]},{"childs":[{"name":"path","closed":true,"segments":[{"point":[2.2,26.5]},{"point":[2.2,3.5]},{"point":[29.8,3.5]},{"point":[29.8,26.5]}]},{"name":"path","closed":true,"fill":"#c0c0c0","segments":[{"point":[2.2,5.8],"handleOut":[2.2,4.53]},{"point":[4.5,3.5],"handleIn":[3.23,3.5]},{"point":[27.5,3.5],"handleOut":[28.77,3.5]},{"point":[29.8,5.8],"handleIn":[29.8,4.53]},{"point":[29.8,8.1]},{"point":[2.2,8.1]}]},{"name":"path","closed":true,"segments":[{"point":[2.2,5.8],"handleOut":[2.2,4.53]},{"point":[4.5,3.5],"handleIn":[3.23,3.5]},{"point":[27.5,3.5],"handleOut":[28.77,3.5]},{"point":[29.8,5.8],"handleIn":[29.8,4.53]},{"point":[29.8,8.1]},{"point":[2.2,8.1]}]},{"name":"path","closed":true,"segments":[{"point":[2.2,8.1]},{"point":[29.8,8.1]},{"point":[29.8,21.9]},{"point":[2.2,21.9]}]},{"name":"path","closed":true,"segments":[{"point":[2.2,8.1]},{"point":[29.8,8.1]},{"point":[29.8,21.9]},{"point":[2.2,21.9]}]},{"name":"path","closed":false,"segments":[{"point":[13.56,18.91]},{"point":[13.56,21.67]}]},{"name":"path","closed":false,"segments":[{"point":[14.39,18.91]},{"point":[14.39,21.67]}]},{"name":"path","closed":false,"segments":[{"point":[15.22,18.91]},{"point":[15.22,21.67]}]},{"name":"path","closed":true,"segments":[{"point":[16,21.9]},{"point":[16,18.68]},{"point":[19.22,18.68]},{"point":[19.22,21.9]}]},{"name":"path","closed":false,"segments":[{"point":[16.92,20.29]},{"point":[18.3,20.29]}]},{"name":"path","closed":false,"segments":[{"point":[17.61,19.6]},{"point":[17.61,20.98]}]},{"name":"path","closed":true,"segments":[{"point":[2.2,21.9]},{"point":[29.8,21.9]},{"point":[29.8,24.2],"handleOut":[29.8,25.47]},{"point":[27.5,26.5],"handleIn":[28.77,26.5]},{"point":[4.5,26.5],"handleOut":[3.23,26.5]},{"point":[2.2,24.2],"handleIn":[2.2,25.47]}]},{"name":"path","closed":true,"segments":[{"point":[2.2,21.9]},{"point":[29.8,21.9]},{"point":[29.8,24.2],"handleOut":[29.8,25.47]},{"point":[27.5,26.5],"handleIn":[28.77,26.5]},{"point":[4.5,26.5],"handleOut":[3.23,26.5]},{"point":[2.2,24.2],"handleIn":[2.2,25.47]}]}]},{"childs":[{"name":"path","closed":true,"segments":[{"point":[1.6,15],"handleOut":[1.6,13.67]},{"point":[4,12.6],"handleIn":[2.67,12.6]},{"point":[28,12.6],"handleOut":[29.33,12.6]},{"point":[30.4,15],"handleIn":[30.4,13.67]},{"point":[30.4,17.4]},{"point":[1.6,17.4]}]},{"name":"path","closed":true,"segments":[{"point":[1.6,15],"handleOut":[1.6,13.67]},{"point":[4,12.6],"handleIn":[2.67,12.6]},{"point":[28,12.6],"handleOut":[29.33,12.6]},{"point":[30.4,15],"handleIn":[30.4,13.67]},{"point":[30.4,17.4]},{"point":[1.6,17.4]}]}]},{"childs":[{"name":"path","closed":true,"segments":[{"point":[1.6,22.2],"handleOut":[1.6,20.87]},{"point":[4,19.8],"handleIn":[2.67,19.8]},{"point":[28,19.8],"handleOut":[29.33,19.8]},{"point":[30.4,22.2],"handleIn":[30.4,20.87]},{"point":[30.4,24.6]},{"point":[1.6,24.6]}]},{"name":"path","closed":true,"segments":[{"point":[1.6,22.2],"handleOut":[1.6,20.87]},{"point":[4,19.8],"handleIn":[2.67,19.8]},{"point":[28,19.8],"handleOut":[29.33,19.8]},{"point":[30.4,22.2],"handleIn":[30.4,20.87]},{"point":[30.4,24.6]},{"point":[1.6,24.6]}]},{"name":"path","closed":true,"segments":[{"point":[11.2,5.4]},{"point":[20.8,5.4]},{"point":[20.8,12.6]},{"point":[11.2,12.6]}]},{"name":"path","closed":false,"segments":[{"point":[11.2,5.4]},{"point":[16,9]},{"point":[20.8,5.4]}]},{"name":"path","closed":false,"segments":[{"point":[16,19.8]},{"point":[16,12.6]}]}]},{"childs":[{"name":"path","closed":true,"segments":[{"point":[1.6,12.6]},{"point":[30.4,12.6]},{"point":[30.4,17.4]},{"point":[1.6,17.4]}]},{"name":"path","closed":true,"segments":[{"point":[1.6,12.6]},{"point":[30.4,12.6]},{"point":[30.4,17.4]},{"point":[1.6,17.4]}]}]},{"childs":[{"name":"path","closed":true,"segments":[{"point":[1.6,12.6]},{"point":[30.4,12.6]},{"point":[30.4,15],"handleOut":[30.4,16.33]},{"point":[28,17.4],"handleIn":[29.33,17.4]},{"point":[4,17.4],"handleOut":[2.67,17.4]},{"point":[1.6,15],"handleIn":[1.6,16.33]}]},{"name":"path","closed":true,"segments":[{"point":[1.6,12.6]},{"point":[30.4,12.6]},{"point":[30.4,15],"handleOut":[30.4,16.33]},{"point":[28,17.4],"handleIn":[29.33,17.4]},{"point":[4,17.4],"handleOut":[2.67,17.4]},{"point":[1.6,15],"handleIn":[1.6,16.33]}]}]},{"childs":[{"name":"path","closed":true,"segments":[{"point":[1.6,5.4]},{"point":[30.4,5.4]},{"point":[30.4,7.8],"handleOut":[30.4,9.13]},{"point":[28,10.2],"handleIn":[29.33,10.2]},{"point":[4,10.2],"handleOut":[2.67,10.2]},{"point":[1.6,7.8],"handleIn":[1.6,9.13]}]},{"name":"path","closed":true,"segments":[{"point":[1.6,5.4]},{"point":[30.4,5.4]},{"point":[30.4,7.8],"handleOut":[30.4,9.13]},{"point":[28,10.2],"handleIn":[29.33,10.2]},{"point":[4,10.2],"handleOut":[2.67,10.2]},{"point":[1.6,7.8],"handleIn":[1.6,9.13]}]},{"name":"path","closed":true,"segments":[{"point":[11.2,17.4]},{"point":[20.8,17.4]},{"point":[20.8,24.6]},{"point":[11.2,24.6]}]},{"name":"path","closed":false,"segments":[{"point":[11.2,17.4]},{"point":[16,21]},{"point":[20.8,17.4]}]},{"name":"path","closed":false,"segments":[{"point":[16,10.2]},{"point":[16,17.4]}]}]},{"childs":[{"name":"path","closed":true,"segments":[{"point":[1.6,12.6],"handleOut":[1.6,11.27]},{"point":[4,10.2],"handleIn":[2.67,10.2]},{"point":[28,10.2],"handleOut":[29.33,10.2]},{"point":[30.4,12.6],"handleIn":[30.4,11.27]},{"point":[30.4,19.8]},{"point":[1.6,19.8]}]},{"name":"path","closed":true,"segments":[{"point":[1.6,12.6],"handleOut":[1.6,11.27]},{"point":[4,10.2],"handleIn":[2.67,10.2]},{"point":[28,10.2],"handleOut":[29.33,10.2]},{"point":[30.4,12.6],"handleIn":[30.4,11.27]},{"point":[30.4,19.8]},{"point":[1.6,19.8]}]},{"name":"path","closed":false,"segments":[{"point":[15.14,16.68]},{"point":[15.14,19.56]}]},{"name":"path","closed":false,"segments":[{"point":[16,16.68]},{"point":[16,19.56]}]},{"name":"path","closed":false,"segments":[{"point":[16.86,16.68]},{"point":[16.86,19.56]}]}]},{"childs":[{"name":"path","closed":true,"segments":[{"point":[1.6,19.8],"handleOut":[1.6,18.47]},{"point":[4,17.4],"handleIn":[2.67,17.4]},{"point":[28,17.4],"handleOut":[29.33,17.4]},{"point":[30.4,19.8],"handleIn":[30.4,18.47]},{"point":[30.4,27]},{"point":[1.6,27]}]},{"name":"path","closed":true,"segments":[{"point":[1.6,19.8],"handleOut":[1.6,18.47]},{"point":[4,17.4],"handleIn":[2.67,17.4]},{"point":[28,17.4],"handleOut":[29.33,17.4]},{"point":[30.4,19.8],"handleIn":[30.4,18.47]},{"point":[30.4,27]},{"point":[1.6,27]}]},{"name":"path","closed":false,"segments":[{"point":[15.14,23.88]},{"point":[15.14,26.76]}]},{"name":"path","closed":false,"segments":[{"point":[16,23.88]},{"point":[16,26.76]}]},{"name":"path","closed":false,"segments":[{"point":[16.86,23.88]},{"point":[16.86,26.76]}]},{"name":"path","closed":true,"segments":[{"point":[11.2,3]},{"point":[20.8,3]},{"point":[20.8,10.2]},{"point":[11.2,10.2]}]},{"name":"path","closed":false,"segments":[{"point":[11.2,3]},{"point":[16,6.6]},{"point":[20.8,3]}]},{"name":"path","closed":false,"segments":[{"point":[16,17.4]},{"point":[16,10.2]}]}]},{"childs":[{"name":"path","closed":true,"segments":[{"point":[1.6,10.2]},{"point":[30.4,10.2]},{"point":[30.4,19.8]},{"point":[1.6,19.8]}]},{"name":"path","closed":true,"segments":[{"point":[1.6,10.2]},{"point":[30.4,10.2]},{"point":[30.4,19.8]},{"point":[1.6,19.8]}]},{"name":"path","closed":false,"segments":[{"point":[15.14,16.68]},{"point":[15.14,19.56]}]},{"name":"path","closed":false,"segments":[{"point":[16,16.68]},{"point":[16,19.56]}]},{"name":"path","closed":false,"segments":[{"point":[16.86,16.68]},{"point":[16.86,19.56]}]}]},{"childs":[{"name":"path","closed":true,"segments":[{"point":[1.6,10.2]},{"point":[30.4,10.2]},{"point":[30.4,17.4],"handleOut":[30.4,18.73]},{"point":[28,19.8],"handleIn":[29.33,19.8]},{"point":[4,19.8],"handleOut":[2.67,19.8]},{"point":[1.6,17.4],"handleIn":[1.6,18.73]}]},{"name":"path","closed":true,"segments":[{"point":[1.6,10.2]},{"point":[30.4,10.2]},{"point":[30.4,17.4],"handleOut":[30.4,18.73]},{"point":[28,19.8],"handleIn":[29.33,19.8]},{"point":[4,19.8],"handleOut":[2.67,19.8]},{"point":[1.6,17.4],"handleIn":[1.6,18.73]}]},{"name":"path","closed":false,"segments":[{"point":[15.14,16.68]},{"point":[15.14,19.56]}]},{"name":"path","closed":false,"segments":[{"point":[16,16.68]},{"point":[16,19.56]}]},{"name":"path","closed":false,"segments":[{"point":[16.86,16.68]},{"point":[16.86,19.56]}]}]},{"childs":[{"name":"path","closed":true,"segments":[{"point":[1.6,3]},{"point":[30.4,3]},{"point":[30.4,10.2],"handleOut":[30.4,11.53]},{"point":[28,12.6],"handleIn":[29.33,12.6]},{"point":[4,12.6],"handleOut":[2.67,12.6]},{"point":[1.6,10.2],"handleIn":[1.6,11.53]}]},{"name":"path","closed":true,"segments":[{"point":[1.6,3]},{"point":[30.4,3]},{"point":[30.4,10.2],"handleOut":[30.4,11.53]},{"point":[28,12.6],"handleIn":[29.33,12.6]},{"point":[4,12.6],"handleOut":[2.67,12.6]},{"point":[1.6,10.2],"handleIn":[1.6,11.53]}]},{"name":"path","closed":false,"segments":[{"point":[15.14,9.48]},{"point":[15.14,12.36]}]},{"name":"path","closed":false,"segments":[{"point":[16,9.48]},{"point":[16,12.36]}]},{"name":"path","closed":false,"segments":[{"point":[16.86,9.48]},{"point":[16.86,12.36]}]},{"name":"path","closed":true,"segments":[{"point":[11.2,19.8]},{"point":[20.8,19.8]},{"point":[20.8,27]},{"point":[11.2,27]}]},{"name":"path","closed":false,"segments":[{"point":[11.2,19.8]},{"point":[16,23.4]},{"point":[20.8,19.8]}]},{"name":"path","closed":false,"segments":[{"point":[16,12.6]},{"point":[16,19.8]}]}]},{"childs":[{"name":"path","closed":true,"fill":"#c0c0c0","segments":[{"point":[1.6,15],"handleOut":[1.6,13.67]},{"point":[4,12.6],"handleIn":[2.67,12.6]},{"point":[28,12.6],"handleOut":[29.33,12.6]},{"point":[30.4,15],"handleIn":[30.4,13.67]},{"point":[30.4,17.4]},{"point":[1.6,17.4]}]},{"name":"path","closed":true,"segments":[{"point":[1.6,15],"handleOut":[1.6,13.67]},{"point":[4,12.6],"handleIn":[2.67,12.6]},{"point":[28,12.6],"handleOut":[29.33,12.6]},{"point":[30.4,15],"handleIn":[30.4,13.67]},{"point":[30.4,17.4]},{"point":[1.6,17.4]}]}]},{"childs":[{"name":"path","closed":true,"fill":"#c0c0c0","segments":[{"point":[1.6,22.2],"handleOut":[1.6,20.87]},{"point":[4,19.8],"handleIn":[2.67,19.8]},{"point":[28,19.8],"handleOut":[29.33,19.8]},{"point":[30.4,22.2],"handleIn":[30.4,20.87]},{"point":[30.4,24.6]},{"point":[1.6,24.6]}]},{"name":"path","closed":true,"segments":[{"point":[1.6,22.2],"handleOut":[1.6,20.87]},{"point":[4,19.8],"handleIn":[2.67,19.8]},{"point":[28,19.8],"handleOut":[29.33,19.8]},{"point":[30.4,22.2],"handleIn":[30.4,20.87]},{"point":[30.4,24.6]},{"point":[1.6,24.6]}]},{"name":"path","closed":true,"fill":"#c0c0c0","segments":[{"point":[11.2,5.4]},{"point":[20.8,5.4]},{"point":[20.8,12.6]},{"point":[11.2,12.6]}]},{"name":"path","closed":false,"segments":[{"point":[11.2,5.4]},{"point":[16,9]},{"point":[20.8,5.4]}]},{"name":"path","closed":false,"segments":[{"point":[16,19.8]},{"point":[16,12.6]}]}]},{"childs":[{"name":"path","closed":true,"fill":"#c0c0c0","segments":[{"point":[1.6,12.6]},{"point":[30.4,12.6]},{"point":[30.4,17.4]},{"point":[1.6,17.4]}]},{"name":"path","closed":true,"segments":[{"point":[1.6,12.6]},{"point":[30.4,12.6]},{"point":[30.4,17.4]},{"point":[1.6,17.4]}]}]},{"childs":[{"name":"path","closed":true,"fill":"#c0c0c0","segments":[{"point":[1.6,12.6]},{"point":[30.4,12.6]},{"point":[30.4,15],"handleOut":[30.4,16.33]},{"point":[28,17.4],"handleIn":[29.33,17.4]},{"point":[4,17.4],"handleOut":[2.67,17.4]},{"point":[1.6,15],"handleIn":[1.6,16.33]}]},{"name":"path","closed":true,"segments":[{"point":[1.6,12.6]},{"point":[30.4,12.6]},{"point":[30.4,15],"handleOut":[30.4,16.33]},{"point":[28,17.4],"handleIn":[29.33,17.4]},{"point":[4,17.4],"handleOut":[2.67,17.4]},{"point":[1.6,15],"handleIn":[1.6,16.33]}]}]},{"childs":[{"name":"path","closed":true,"fill":"#c0c0c0","segments":[{"point":[1.6,5.4]},{"point":[30.4,5.4]},{"point":[30.4,7.8],"handleOut":[30.4,9.13]},{"point":[28,10.2],"handleIn":[29.33,10.2]},{"point":[4,10.2],"handleOut":[2.67,10.2]},{"point":[1.6,7.8],"handleIn":[1.6,9.13]}]},{"name":"path","closed":true,"segments":[{"point":[1.6,5.4]},{"point":[30.4,5.4]},{"point":[30.4,7.8],"handleOut":[30.4,9.13]},{"point":[28,10.2],"handleIn":[29.33,10.2]},{"point":[4,10.2],"handleOut":[2.67,10.2]},{"point":[1.6,7.8],"handleIn":[1.6,9.13]}]},{"name":"path","closed":true,"fill":"#c0c0c0","segments":[{"point":[11.2,17.4]},{"point":[20.8,17.4]},{"point":[20.8,24.6]},{"point":[11.2,24.6]}]},{"name":"path","closed":false,"segments":[{"point":[11.2,17.4]},{"point":[16,21]},{"point":[20.8,17.4]}]},{"name":"path","closed":false,"segments":[{"point":[16,10.2]},{"point":[16,17.4]}]}]},{"childs":[{"name":"path","closed":true,"fill":"#c0c0c0","segments":[{"point":[1.6,12.6],"handleOut":[1.6,11.27]},{"point":[4,10.2],"handleIn":[2.67,10.2]},{"point":[28,10.2],"handleOut":[29.33,10.2]},{"point":[30.4,12.6],"handleIn":[30.4,11.27]},{"point":[30.4,19.8]},{"point":[1.6,19.8]}]},{"name":"path","closed":true,"segments":[{"point":[1.6,12.6],"handleOut":[1.6,11.27]},{"point":[4,10.2],"handleIn":[2.67,10.2]},{"point":[28,10.2],"handleOut":[29.33,10.2]},{"point":[30.4,12.6],"handleIn":[30.4,11.27]},{"point":[30.4,19.8]},{"point":[1.6,19.8]}]},{"name":"path","closed":false,"segments":[{"point":[15.14,16.68]},{"point":[15.14,19.56]}]},{"name":"path","closed":false,"segments":[{"point":[16,16.68]},{"point":[16,19.56]}]},{"name":"path","closed":false,"segments":[{"point":[16.86,16.68]},{"point":[16.86,19.56]}]}]},{"childs":[{"name":"path","closed":true,"fill":"#c0c0c0","segments":[{"point":[1.6,19.8],"handleOut":[1.6,18.47]},{"point":[4,17.4],"handleIn":[2.67,17.4]},{"point":[28,17.4],"handleOut":[29.33,17.4]},{"point":[30.4,19.8],"handleIn":[30.4,18.47]},{"point":[30.4,27]},{"point":[1.6,27]}]},{"name":"path","closed":true,"segments":[{"point":[1.6,19.8],"handleOut":[1.6,18.47]},{"point":[4,17.4],"handleIn":[2.67,17.4]},{"point":[28,17.4],"handleOut":[29.33,17.4]},{"point":[30.4,19.8],"handleIn":[30.4,18.47]},{"point":[30.4,27]},{"point":[1.6,27]}]},{"name":"path","closed":false,"segments":[{"point":[15.14,23.88]},{"point":[15.14,26.76]}]},{"name":"path","closed":false,"segments":[{"point":[16,23.88]},{"point":[16,26.76]}]},{"name":"path","closed":false,"segments":[{"point":[16.86,23.88]},{"point":[16.86,26.76]}]},{"name":"path","closed":true,"fill":"#c0c0c0","segments":[{"point":[11.2,3]},{"point":[20.8,3]},{"point":[20.8,10.2]},{"point":[11.2,10.2]}]},{"name":"path","closed":false,"segments":[{"point":[11.2,3]},{"point":[16,6.6]},{"point":[20.8,3]}]},{"name":"path","closed":false,"segments":[{"point":[16,17.4]},{"point":[16,10.2]}]}]},{"childs":[{"name":"path","closed":true,"fill":"#c0c0c0","segments":[{"point":[1.6,10.2]},{"point":[30.4,10.2]},{"point":[30.4,19.8]},{"point":[1.6,19.8]}]},{"name":"path","closed":true,"segments":[{"point":[1.6,10.2]},{"point":[30.4,10.2]},{"point":[30.4,19.8]},{"point":[1.6,19.8]}]},{"name":"path","closed":false,"segments":[{"point":[15.14,16.68]},{"point":[15.14,19.56]}]},{"name":"path","closed":false,"segments":[{"point":[16,16.68]},{"point":[16,19.56]}]},{"name":"path","closed":false,"segments":[{"point":[16.86,16.68]},{"point":[16.86,19.56]}]}]},{"childs":[{"name":"path","closed":true,"fill":"#c0c0c0","segments":[{"point":[1.6,10.2]},{"point":[30.4,10.2]},{"point":[30.4,17.4],"handleOut":[30.4,18.73]},{"point":[28,19.8],"handleIn":[29.33,19.8]},{"point":[4,19.8],"handleOut":[2.67,19.8]},{"point":[1.6,17.4],"handleIn":[1.6,18.73]}]},{"name":"path","closed":true,"segments":[{"point":[1.6,10.2]},{"point":[30.4,10.2]},{"point":[30.4,17.4],"handleOut":[30.4,18.73]},{"point":[28,19.8],"handleIn":[29.33,19.8]},{"point":[4,19.8],"handleOut":[2.67,19.8]},{"point":[1.6,17.4],"handleIn":[1.6,18.73]}]},{"name":"path","closed":false,"segments":[{"point":[15.14,16.68]},{"point":[15.14,19.56]}]},{"name":"path","closed":false,"segments":[{"point":[16,16.68]},{"point":[16,19.56]}]},{"name":"path","closed":false,"segments":[{"point":[16.86,16.68]},{"point":[16.86,19.56]}]}]},{"childs":[{"name":"path","closed":true,"fill":"#c0c0c0","segments":[{"point":[1.6,3]},{"point":[30.4,3]},{"point":[30.4,10.2],"handleOut":[30.4,11.53]},{"point":[28,12.6],"handleIn":[29.33,12.6]},{"point":[4,12.6],"handleOut":[2.67,12.6]},{"point":[1.6,10.2],"handleIn":[1.6,11.53]}]},{"name":"path","closed":true,"segments":[{"point":[1.6,3]},{"point":[30.4,3]},{"point":[30.4,10.2],"handleOut":[30.4,11.53]},{"point":[28,12.6],"handleIn":[29.33,12.6]},{"point":[4,12.6],"handleOut":[2.67,12.6]},{"point":[1.6,10.2],"handleIn":[1.6,11.53]}]},{"name":"path","closed":false,"segments":[{"point":[15.14,9.48]},{"point":[15.14,12.36]}]},{"name":"path","closed":false,"segments":[{"point":[16,9.48]},{"point":[16,12.36]}]},{"name":"path","closed":false,"segments":[{"point":[16.86,9.48]},{"point":[16.86,12.36]}]},{"name":"path","closed":true,"fill":"#c0c0c0","segments":[{"point":[11.2,19.8]},{"point":[20.8,19.8]},{"point":[20.8,27]},{"point":[11.2,27]}]},{"name":"path","closed":false,"segments":[{"point":[11.2,19.8]},{"point":[16,23.4]},{"point":[20.8,19.8]}]},{"name":"path","closed":false,"segments":[{"point":[16,12.6]},{"point":[16,19.8]}]}]}]